{
"meta":{"test_sets":[],"test_metrics":[],"learn_metrics":[{"best_value":"Min","name":"RMSE"}],"launch_mode":"Train","parameters":"","iteration_count":1000,"learn_sets":["learn"],"name":"experiment"},
"iterations":[
{"learn":[1.030642319],"iteration":0,"passed_time":0.0007581875327,"remaining_time":0.7574293451},
{"learn":[1.023933652],"iteration":1,"passed_time":0.001951023742,"remaining_time":0.9735608473},
{"learn":[1.017843616],"iteration":2,"passed_time":0.002864415976,"remaining_time":0.9519409093},
{"learn":[1.010925271],"iteration":3,"passed_time":0.003972271232,"remaining_time":0.9890955369},
{"learn":[1.003204579],"iteration":4,"passed_time":0.005065582669,"remaining_time":1.008050951},
{"learn":[0.996283562],"iteration":5,"passed_time":0.005819296648,"remaining_time":0.964063478},
{"learn":[0.9902930308],"iteration":6,"passed_time":0.006973908324,"remaining_time":0.9892987094},
{"learn":[0.9825959185],"iteration":7,"passed_time":0.00812590164,"remaining_time":1.007611803},
{"learn":[0.9761695529],"iteration":8,"passed_time":0.008688830349,"remaining_time":0.956736764},
{"learn":[0.9698565304],"iteration":9,"passed_time":0.009837127335,"remaining_time":0.9738756062},
{"learn":[0.9637085955],"iteration":10,"passed_time":0.01092063812,"remaining_time":0.9818646459},
{"learn":[0.9601666279],"iteration":11,"passed_time":0.01195535103,"remaining_time":0.9843239013},
{"learn":[0.9533527259],"iteration":12,"passed_time":0.01391149099,"remaining_time":1.0562032},
{"learn":[0.9470415538],"iteration":13,"passed_time":0.01524710536,"remaining_time":1.073831849},
{"learn":[0.9411145141],"iteration":14,"passed_time":0.01646145178,"remaining_time":1.080968667},
{"learn":[0.934614566],"iteration":15,"passed_time":0.01775824967,"remaining_time":1.092132354},
{"learn":[0.9283557396],"iteration":16,"passed_time":0.01941539858,"remaining_time":1.122666871},
{"learn":[0.9221465128],"iteration":17,"passed_time":0.02063458207,"remaining_time":1.125731088},
{"learn":[0.9151678256],"iteration":18,"passed_time":0.02210757521,"remaining_time":1.141449015},
{"learn":[0.9093683289],"iteration":19,"passed_time":0.02335906869,"remaining_time":1.144594366},
{"learn":[0.9024285504],"iteration":20,"passed_time":0.02418391368,"remaining_time":1.127431024},
{"learn":[0.8966031042],"iteration":21,"passed_time":0.02475386,"remaining_time":1.100421594},
{"learn":[0.8910871599],"iteration":22,"passed_time":0.02590978412,"remaining_time":1.100602569},
{"learn":[0.8853330558],"iteration":23,"passed_time":0.02709731382,"remaining_time":1.101957429},
{"learn":[0.8786445245],"iteration":24,"passed_time":0.02866745287,"remaining_time":1.118030662},
{"learn":[0.87199054],"iteration":25,"passed_time":0.02978031087,"remaining_time":1.115616261},
{"learn":[0.8659726194],"iteration":26,"passed_time":0.03103706317,"remaining_time":1.118483795},
{"learn":[0.8606929162],"iteration":27,"passed_time":0.03158917753,"remaining_time":1.096595734},
{"learn":[0.8556579924],"iteration":28,"passed_time":0.0328255252,"remaining_time":1.099089137},
{"learn":[0.8493003456],"iteration":29,"passed_time":0.03362698721,"remaining_time":1.087272586},
{"learn":[0.843130506],"iteration":30,"passed_time":0.03476661825,"remaining_time":1.086737196},
{"learn":[0.8374214323],"iteration":31,"passed_time":0.03585828687,"remaining_time":1.084713178},
{"learn":[0.8327359605],"iteration":32,"passed_time":0.03729876516,"remaining_time":1.092966846},
{"learn":[0.8271339763],"iteration":33,"passed_time":0.03858082994,"remaining_time":1.096149462},
{"learn":[0.8209790917],"iteration":34,"passed_time":0.04001219895,"remaining_time":1.103193485},
{"learn":[0.8148943993],"iteration":35,"passed_time":0.04132085501,"remaining_time":1.106480673},
{"learn":[0.8094089431],"iteration":36,"passed_time":0.04301569124,"remaining_time":1.119570558},
{"learn":[0.8040609586],"iteration":37,"passed_time":0.04444008883,"remaining_time":1.125035933},
{"learn":[0.7997479132],"iteration":38,"passed_time":0.04573795665,"remaining_time":1.127030163},
{"learn":[0.7944479038],"iteration":39,"passed_time":0.04693978014,"remaining_time":1.126554723},
{"learn":[0.7888815394],"iteration":40,"passed_time":0.04819420076,"remaining_time":1.12727411},
{"learn":[0.7846274595],"iteration":41,"passed_time":0.04955094477,"remaining_time":1.130233454},
{"learn":[0.7795085745],"iteration":42,"passed_time":0.05078116954,"remaining_time":1.130176262},
{"learn":[0.7737988905],"iteration":43,"passed_time":0.05212369056,"remaining_time":1.13250564},
{"learn":[0.7696430521],"iteration":44,"passed_time":0.05344860907,"remaining_time":1.134298259},
{"learn":[0.764372304],"iteration":45,"passed_time":0.05417484559,"remaining_time":1.123539189},
{"learn":[0.7597167134],"iteration":46,"passed_time":0.05472713166,"remaining_time":1.109679925},
{"learn":[0.7556051846],"iteration":47,"passed_time":0.05589177544,"remaining_time":1.108520213},
{"learn":[0.7510800387],"iteration":48,"passed_time":0.05717099643,"remaining_time":1.109584033},
{"learn":[0.7466354038],"iteration":49,"passed_time":0.05858478352,"remaining_time":1.113110887},
{"learn":[0.7423300852],"iteration":50,"passed_time":0.05935142461,"remaining_time":1.104401999},
{"learn":[0.7385884406],"iteration":51,"passed_time":0.06042994119,"remaining_time":1.101684312},
{"learn":[0.7347069165],"iteration":52,"passed_time":0.06145302586,"remaining_time":1.098038028},
{"learn":[0.7304664585],"iteration":53,"passed_time":0.06267837391,"remaining_time":1.098032254},
{"learn":[0.7256115314],"iteration":54,"passed_time":0.06400777552,"remaining_time":1.099769961},
{"learn":[0.7219496433],"iteration":55,"passed_time":0.0652621625,"remaining_time":1.100133597},
{"learn":[0.7167540895],"iteration":56,"passed_time":0.06691112296,"remaining_time":1.106968227},
{"learn":[0.7126396671],"iteration":57,"passed_time":0.06814178153,"remaining_time":1.106716521},
{"learn":[0.7076712817],"iteration":58,"passed_time":0.06934290562,"remaining_time":1.105960579},
{"learn":[0.7032291301],"iteration":59,"passed_time":0.07059896906,"remaining_time":1.106050515},
{"learn":[0.6994238532],"iteration":60,"passed_time":0.07236377397,"remaining_time":1.113927603},
{"learn":[0.6953301289],"iteration":61,"passed_time":0.07297683761,"remaining_time":1.10406893},
{"learn":[0.6913368799],"iteration":62,"passed_time":0.0741535635,"remaining_time":1.102887127},
{"learn":[0.6871772601],"iteration":63,"passed_time":0.07544677401,"remaining_time":1.10340907},
{"learn":[0.6834434271],"iteration":64,"passed_time":0.07687774486,"remaining_time":1.105856792},
{"learn":[0.6792811468],"iteration":65,"passed_time":0.0777312211,"remaining_time":1.100014553},
{"learn":[0.675430479],"iteration":66,"passed_time":0.07904172784,"remaining_time":1.100685553},
{"learn":[0.6715715086],"iteration":67,"passed_time":0.08019373672,"remaining_time":1.099125921},
{"learn":[0.6685200946],"iteration":68,"passed_time":0.08135094617,"remaining_time":1.097648274},
{"learn":[0.6655940539],"iteration":69,"passed_time":0.08239715776,"remaining_time":1.094705096},
{"learn":[0.6623664443],"iteration":70,"passed_time":0.0833543607,"remaining_time":1.09065072},
{"learn":[0.6576489329],"iteration":71,"passed_time":0.08460309876,"remaining_time":1.09043994},
{"learn":[0.6537403758],"iteration":72,"passed_time":0.08588213548,"remaining_time":1.090585474},
{"learn":[0.6499669965],"iteration":73,"passed_time":0.08750581358,"remaining_time":1.095005181},
{"learn":[0.6454033934],"iteration":74,"passed_time":0.08859237452,"remaining_time":1.092639286},
{"learn":[0.6417286356],"iteration":75,"passed_time":0.08913010622,"remaining_time":1.083634449},
{"learn":[0.6379828167],"iteration":76,"passed_time":0.09024658776,"remaining_time":1.081787019},
{"learn":[0.6339254565],"iteration":77,"passed_time":0.09146155626,"remaining_time":1.081122498},
{"learn":[0.6310711078],"iteration":78,"passed_time":0.09259769783,"remaining_time":1.07952506},
{"learn":[0.6277980402],"iteration":79,"passed_time":0.09372172265,"remaining_time":1.07779981},
{"learn":[0.6235027874],"iteration":80,"passed_time":0.09489611185,"remaining_time":1.076660825},
{"learn":[0.6193932261],"iteration":81,"passed_time":0.09570809851,"remaining_time":1.071463835},
{"learn":[0.615691651],"iteration":82,"passed_time":0.09659441646,"remaining_time":1.067193734},
{"learn":[0.6116786819],"iteration":83,"passed_time":0.09746464266,"remaining_time":1.062828722},
{"learn":[0.6086458714],"iteration":84,"passed_time":0.09848315789,"remaining_time":1.060142229},
{"learn":[0.6044867623],"iteration":85,"passed_time":0.09986172691,"remaining_time":1.061321144},
{"learn":[0.6008906739],"iteration":86,"passed_time":0.1011167099,"remaining_time":1.061144323},
{"learn":[0.5975290748],"iteration":87,"passed_time":0.1021530852,"remaining_time":1.058677428},
{"learn":[0.5940433517],"iteration":88,"passed_time":0.1034757734,"remaining_time":1.059173366},
{"learn":[0.5903325226],"iteration":89,"passed_time":0.1043559424,"remaining_time":1.055154528},
{"learn":[0.5876136436],"iteration":90,"passed_time":0.1054000377,"remaining_time":1.052842135},
{"learn":[0.5841634417],"iteration":91,"passed_time":0.1064615061,"remaining_time":1.050728777},
{"learn":[0.5801855406],"iteration":92,"passed_time":0.1073914459,"remaining_time":1.047355284},
{"learn":[0.5761646649],"iteration":93,"passed_time":0.1087977209,"remaining_time":1.048624841},
{"learn":[0.5721922863],"iteration":94,"passed_time":0.109825852,"remaining_time":1.046235748},
{"learn":[0.5685751607],"iteration":95,"passed_time":0.1105327176,"remaining_time":1.040849758},
{"learn":[0.564716413],"iteration":96,"passed_time":0.1115176074,"remaining_time":1.038148448},
{"learn":[0.5620675947],"iteration":97,"passed_time":0.1128825092,"remaining_time":1.03897983},
{"learn":[0.5588767791],"iteration":98,"passed_time":0.1139316409,"remaining_time":1.036893015},
{"learn":[0.5561420389],"iteration":99,"passed_time":0.114971928,"remaining_time":1.034747352},
{"learn":[0.5532804222],"iteration":100,"passed_time":0.1162942693,"remaining_time":1.03513414},
{"learn":[0.5495322545],"iteration":101,"passed_time":0.117949077,"remaining_time":1.038414423},
{"learn":[0.5463612967],"iteration":102,"passed_time":0.1186531119,"remaining_time":1.033318849},
{"learn":[0.5428136108],"iteration":103,"passed_time":0.1193160821,"remaining_time":1.027953938},
{"learn":[0.5396816102],"iteration":104,"passed_time":0.1204019321,"remaining_time":1.026283135},
{"learn":[0.5366195167],"iteration":105,"passed_time":0.1217045591,"remaining_time":1.026451659},
{"learn":[0.5339135676],"iteration":106,"passed_time":0.1229687513,"remaining_time":1.026271915},
{"learn":[0.5302628315],"iteration":107,"passed_time":0.1238983311,"remaining_time":1.023308439},
{"learn":[0.5273810249],"iteration":108,"passed_time":0.1248199314,"remaining_time":1.020317054},
{"learn":[0.5238017501],"iteration":109,"passed_time":0.1261509271,"remaining_time":1.020675683},
{"learn":[0.5208611845],"iteration":110,"passed_time":0.1273420527,"remaining_time":1.019883648},
{"learn":[0.5176623454],"iteration":111,"passed_time":0.1284755293,"remaining_time":1.018627411},
{"learn":[0.5141497914],"iteration":112,"passed_time":0.1294696091,"remaining_time":1.016279144},
{"learn":[0.5109682977],"iteration":113,"passed_time":0.130592669,"remaining_time":1.014957059},
{"learn":[0.5080237148],"iteration":114,"passed_time":0.1319625384,"remaining_time":1.015537796},
{"learn":[0.5046064457],"iteration":115,"passed_time":0.1335701705,"remaining_time":1.017896816},
{"learn":[0.5020715744],"iteration":116,"passed_time":0.1346704458,"remaining_time":1.016359005},
{"learn":[0.4991905343],"iteration":117,"passed_time":0.1357912061,"remaining_time":1.014981727},
{"learn":[0.4963644514],"iteration":118,"passed_time":0.1371373983,"remaining_time":1.015277713},
{"learn":[0.4933563055],"iteration":119,"passed_time":0.1384183078,"remaining_time":1.01506759},
{"learn":[0.4900595509],"iteration":120,"passed_time":0.1392518217,"remaining_time":1.01158968},
{"learn":[0.4867719161],"iteration":121,"passed_time":0.140276258,"remaining_time":1.009529135},
{"learn":[0.4835111731],"iteration":122,"passed_time":0.1413268342,"remaining_time":1.007671818},
{"learn":[0.4807612882],"iteration":123,"passed_time":0.1423990326,"remaining_time":1.005980262},
{"learn":[0.4778128754],"iteration":124,"passed_time":0.1434702107,"remaining_time":1.004291475},
{"learn":[0.4746051562],"iteration":125,"passed_time":0.1449344089,"remaining_time":1.005338677},
{"learn":[0.4714335629],"iteration":126,"passed_time":0.1469142501,"remaining_time":1.009890869},
{"learn":[0.4688257933],"iteration":127,"passed_time":0.1488205795,"remaining_time":1.013840198},
{"learn":[0.4661572897],"iteration":128,"passed_time":0.1501040511,"remaining_time":1.013493244},
{"learn":[0.4636717035],"iteration":129,"passed_time":0.1507477212,"remaining_time":1.008850134},
{"learn":[0.4606231305],"iteration":130,"passed_time":0.1515481605,"remaining_time":1.005308026},
{"learn":[0.4575636027],"iteration":131,"passed_time":0.1527556766,"remaining_time":1.004484297},
{"learn":[0.4545269599],"iteration":132,"passed_time":0.1535794034,"remaining_time":1.001152953},
{"learn":[0.4522487168],"iteration":133,"passed_time":0.1546987549,"remaining_time":0.999769565},
{"learn":[0.4496636066],"iteration":134,"passed_time":0.1558118122,"remaining_time":0.9983497596},
{"learn":[0.4471139842],"iteration":135,"passed_time":0.1569583916,"remaining_time":0.9971474287},
{"learn":[0.4445462356],"iteration":136,"passed_time":0.1581814285,"remaining_time":0.9964275388},
{"learn":[0.4420419561],"iteration":137,"passed_time":0.1593400764,"remaining_time":0.9952981586},
{"learn":[0.4395727006],"iteration":138,"passed_time":0.160879714,"remaining_time":0.9965283003},
{"learn":[0.4366572743],"iteration":139,"passed_time":0.163222244,"remaining_time":1.002650927},
{"learn":[0.4342058274],"iteration":140,"passed_time":0.1646668157,"remaining_time":1.003182941},
{"learn":[0.4320266103],"iteration":141,"passed_time":0.166058714,"remaining_time":1.00336885},
{"learn":[0.4292192789],"iteration":142,"passed_time":0.166756857,"remaining_time":0.9993750104},
{"learn":[0.4271676948],"iteration":143,"passed_time":0.1677688281,"remaining_time":0.9972924783},
{"learn":[0.4243164694],"iteration":144,"passed_time":0.1687714921,"remaining_time":0.9951698328},
{"learn":[0.4222746571],"iteration":145,"passed_time":0.1696256532,"remaining_time":0.9921938892},
{"learn":[0.4194599067],"iteration":146,"passed_time":0.1707434612,"remaining_time":0.9907766831},
{"learn":[0.4167133557],"iteration":147,"passed_time":0.1718267451,"remaining_time":0.9891647757},
{"learn":[0.4141968962],"iteration":148,"passed_time":0.1727900137,"remaining_time":0.9868745075},
{"learn":[0.4120826627],"iteration":149,"passed_time":0.174004463,"remaining_time":0.9860252904},
{"learn":[0.4093747704],"iteration":150,"passed_time":0.1750884859,"remaining_time":0.9844379109},
{"learn":[0.4069207142],"iteration":151,"passed_time":0.1764763174,"remaining_time":0.9845520863},
{"learn":[0.4046494388],"iteration":152,"passed_time":0.1781368548,"remaining_time":0.986156314},
{"learn":[0.4024012047],"iteration":153,"passed_time":0.1789884086,"remaining_time":0.9832739849},
{"learn":[0.4001355803],"iteration":154,"passed_time":0.1800541447,"remaining_time":0.9815854983},
{"learn":[0.3977309347],"iteration":155,"passed_time":0.1811361477,"remaining_time":0.9799930042},
{"learn":[0.3958172899],"iteration":156,"passed_time":0.1821980112,"remaining_time":0.9782988755},
{"learn":[0.3932284277],"iteration":157,"passed_time":0.1830794108,"remaining_time":0.9756510371},
{"learn":[0.3910406324],"iteration":158,"passed_time":0.1841240599,"remaining_time":0.9738888953},
{"learn":[0.3884875681],"iteration":159,"passed_time":0.1849735606,"remaining_time":0.9711111932},
{"learn":[0.3861379627],"iteration":160,"passed_time":0.1860510188,"remaining_time":0.9695453713},
{"learn":[0.3835861046],"iteration":161,"passed_time":0.1871249755,"remaining_time":0.9679674657},
{"learn":[0.3811297045],"iteration":162,"passed_time":0.1878312863,"remaining_time":0.9645078937},
{"learn":[0.3790023574],"iteration":163,"passed_time":0.1890654741,"remaining_time":0.9637727824},
{"learn":[0.3768884356],"iteration":164,"passed_time":0.1903465954,"remaining_time":0.9632691344},
{"learn":[0.3750126958],"iteration":165,"passed_time":0.1924110541,"remaining_time":0.9666916816},
{"learn":[0.3731465637],"iteration":166,"passed_time":0.1933688078,"remaining_time":0.9645282451},
{"learn":[0.370724841],"iteration":167,"passed_time":0.1946516639,"remaining_time":0.9639891927},
{"learn":[0.3683216215],"iteration":168,"passed_time":0.1956239991,"remaining_time":0.9619144571},
{"learn":[0.3662553364],"iteration":169,"passed_time":0.1967289137,"remaining_time":0.9604999902},
{"learn":[0.3638853493],"iteration":170,"passed_time":0.1978386482,"remaining_time":0.9591125109},
{"learn":[0.362076961],"iteration":171,"passed_time":0.1987033575,"remaining_time":0.9565487212},
{"learn":[0.359709536],"iteration":172,"passed_time":0.1998039045,"remaining_time":0.9551319596},
{"learn":[0.357991626],"iteration":173,"passed_time":0.2009115674,"remaining_time":0.9537526133},
{"learn":[0.3559863532],"iteration":174,"passed_time":0.2021725242,"remaining_time":0.9530990426},
{"learn":[0.3536813187],"iteration":175,"passed_time":0.2032664075,"remaining_time":0.9516563623},
{"learn":[0.3518900843],"iteration":176,"passed_time":0.20437637,"remaining_time":0.950292387},
{"learn":[0.3501345282],"iteration":177,"passed_time":0.2057256621,"remaining_time":0.9500364845},
{"learn":[0.3482751377],"iteration":178,"passed_time":0.2068203492,"remaining_time":0.9486005962},
{"learn":[0.3465473954],"iteration":179,"passed_time":0.2084282685,"remaining_time":0.9495065563},
{"learn":[0.3448284722],"iteration":180,"passed_time":0.209507027,"remaining_time":0.9479903599},
{"learn":[0.3431187368],"iteration":181,"passed_time":0.210540657,"remaining_time":0.9462761395},
{"learn":[0.3409008677],"iteration":182,"passed_time":0.2116331841,"remaining_time":0.944832303},
{"learn":[0.3390001016],"iteration":183,"passed_time":0.212670414,"remaining_time":0.9431470533},
{"learn":[0.3374166648],"iteration":184,"passed_time":0.2137873524,"remaining_time":0.9418199579},
{"learn":[0.3356510791],"iteration":185,"passed_time":0.2148985701,"remaining_time":0.9404700864},
{"learn":[0.3334514755],"iteration":186,"passed_time":0.2181230078,"remaining_time":0.9483101888},
{"learn":[0.3316352896],"iteration":187,"passed_time":0.2202806931,"remaining_time":0.9514251213},
{"learn":[0.3298227482],"iteration":188,"passed_time":0.2237096856,"remaining_time":0.9599394447},
{"learn":[0.3279995195],"iteration":189,"passed_time":0.2258031496,"remaining_time":0.96263448},
{"learn":[0.3261766766],"iteration":190,"passed_time":0.2279470769,"remaining_time":0.9654931164},
{"learn":[0.3245921526],"iteration":191,"passed_time":0.2301130718,"remaining_time":0.9683925103},
{"learn":[0.3225139522],"iteration":192,"passed_time":0.2319556613,"remaining_time":0.9698871432},
{"learn":[0.3204348253],"iteration":193,"passed_time":0.2343780219,"remaining_time":0.9737561114},
{"learn":[0.3186897175],"iteration":194,"passed_time":0.2369717878,"remaining_time":0.9782681497},
{"learn":[0.3166562292],"iteration":195,"passed_time":0.2392614074,"remaining_time":0.9814600588},
{"learn":[0.3150534764],"iteration":196,"passed_time":0.2411768149,"remaining_time":0.9830709765},
{"learn":[0.313318824],"iteration":197,"passed_time":0.2439958155,"remaining_time":0.988306283},
{"learn":[0.3116168274],"iteration":198,"passed_time":0.2458917894,"remaining_time":0.9897453434},
{"learn":[0.3100790576],"iteration":199,"passed_time":0.2481242123,"remaining_time":0.9924968491},
{"learn":[0.3080732149],"iteration":200,"passed_time":0.2501830456,"remaining_time":0.9945087237},
{"learn":[0.3065328959],"iteration":201,"passed_time":0.2534960807,"remaining_time":1.001435012},
{"learn":[0.3050009401],"iteration":202,"passed_time":0.2560661027,"remaining_time":1.00534327},
{"learn":[0.303328189],"iteration":203,"passed_time":0.2583421123,"remaining_time":1.008040791},
{"learn":[0.3014032985],"iteration":204,"passed_time":0.2600785667,"remaining_time":1.008597368},
{"learn":[0.2999087974],"iteration":205,"passed_time":0.2623380131,"remaining_time":1.011147487},
{"learn":[0.2984317989],"iteration":206,"passed_time":0.2647548387,"remaining_time":1.014254044},
{"learn":[0.2967860708],"iteration":207,"passed_time":0.2686099651,"remaining_time":1.022784098},
{"learn":[0.2951410171],"iteration":208,"passed_time":0.2707830603,"remaining_time":1.024829669},
{"learn":[0.293528457],"iteration":209,"passed_time":0.2725437477,"remaining_time":1.025283622},
{"learn":[0.2920841762],"iteration":210,"passed_time":0.2748090383,"remaining_time":1.027603466},
{"learn":[0.2905078478],"iteration":211,"passed_time":0.277158253,"remaining_time":1.030191997},
{"learn":[0.2889413406],"iteration":212,"passed_time":0.2790274901,"remaining_time":1.030960726},
{"learn":[0.2875211994],"iteration":213,"passed_time":0.2817333861,"remaining_time":1.034777764},
{"learn":[0.2861085369],"iteration":214,"passed_time":0.2846390687,"remaining_time":1.039263576},
{"learn":[0.2846767351],"iteration":215,"passed_time":0.2868244685,"remaining_time":1.041066589},
{"learn":[0.2830695169],"iteration":216,"passed_time":0.2890881987,"remaining_time":1.043115482},
{"learn":[0.2816072399],"iteration":217,"passed_time":0.2904930101,"remaining_time":1.042043733},
{"learn":[0.2801774881],"iteration":218,"passed_time":0.2927902452,"remaining_time":1.044151514},
{"learn":[0.2787662986],"iteration":219,"passed_time":0.2951455552,"remaining_time":1.04642515},
{"learn":[0.2772485082],"iteration":220,"passed_time":0.2986592615,"remaining_time":1.052740112},
{"learn":[0.2758883101],"iteration":221,"passed_time":0.3009347977,"remaining_time":1.054627354},
{"learn":[0.2745352851],"iteration":222,"passed_time":0.3031381831,"remaining_time":1.056225867},
{"learn":[0.2731664121],"iteration":223,"passed_time":0.3052842934,"remaining_time":1.057592017},
{"learn":[0.2718298805],"iteration":224,"passed_time":0.3074885007,"remaining_time":1.059127058},
{"learn":[0.2703095062],"iteration":225,"passed_time":0.310463902,"remaining_time":1.063270178},
{"learn":[0.2688504606],"iteration":226,"passed_time":0.3145872584,"remaining_time":1.071259695},
{"learn":[0.2674103698],"iteration":227,"passed_time":0.3163524027,"remaining_time":1.071158135},
{"learn":[0.2660781395],"iteration":228,"passed_time":0.3187140183,"remaining_time":1.073050254},
{"learn":[0.2646421623],"iteration":229,"passed_time":0.3204332407,"remaining_time":1.072754762},
{"learn":[0.263339864],"iteration":230,"passed_time":0.3226014557,"remaining_time":1.073941643},
{"learn":[0.2620207828],"iteration":231,"passed_time":0.3248393924,"remaining_time":1.075330402},
{"learn":[0.2607396913],"iteration":232,"passed_time":0.3274781655,"remaining_time":1.078007523},
{"learn":[0.2594343464],"iteration":233,"passed_time":0.3301149625,"remaining_time":1.08063274},
{"learn":[0.2581666269],"iteration":234,"passed_time":0.3322551317,"remaining_time":1.081596493},
{"learn":[0.2569056173],"iteration":235,"passed_time":0.3344575014,"remaining_time":1.082735301},
{"learn":[0.2556512833],"iteration":236,"passed_time":0.3365989067,"remaining_time":1.083649645},
{"learn":[0.2542846197],"iteration":237,"passed_time":0.3388494351,"remaining_time":1.084887687},
{"learn":[0.2530064217],"iteration":238,"passed_time":0.3410116473,"remaining_time":1.085815329},
{"learn":[0.2517620051],"iteration":239,"passed_time":0.3441044324,"remaining_time":1.089664036},
{"learn":[0.2505343689],"iteration":240,"passed_time":0.3463083384,"remaining_time":1.090655721},
{"learn":[0.2493142563],"iteration":241,"passed_time":0.3494882549,"remaining_time":1.094678088},
{"learn":[0.2480999039],"iteration":242,"passed_time":0.3529759303,"remaining_time":1.099599915},
{"learn":[0.2468916504],"iteration":243,"passed_time":0.3555414371,"remaining_time":1.1015956},
{"learn":[0.2456791496],"iteration":244,"passed_time":0.3579559622,"remaining_time":1.103088781},
{"learn":[0.2444634359],"iteration":245,"passed_time":0.3603872272,"remaining_time":1.104601501},
{"learn":[0.2432741788],"iteration":246,"passed_time":0.3626586327,"remaining_time":1.105594941},
{"learn":[0.2420806988],"iteration":247,"passed_time":0.3655037642,"remaining_time":1.108301737},
{"learn":[0.2409040019],"iteration":248,"passed_time":0.3677323908,"remaining_time":1.10910452},
{"learn":[0.2395934804],"iteration":249,"passed_time":0.3700506205,"remaining_time":1.110151861},
{"learn":[0.2384296885],"iteration":250,"passed_time":0.3725097732,"remaining_time":1.111592909},
{"learn":[0.23727209],"iteration":251,"passed_time":0.3753987495,"remaining_time":1.114278828},
{"learn":[0.2361206547],"iteration":252,"passed_time":0.3778852918,"remaining_time":1.115732462},
{"learn":[0.2349753522],"iteration":253,"passed_time":0.380166031,"remaining_time":1.116550626},
{"learn":[0.2338361528],"iteration":254,"passed_time":0.3824177734,"remaining_time":1.117259769},
{"learn":[0.2327030264],"iteration":255,"passed_time":0.3847460056,"remaining_time":1.118168079},
{"learn":[0.2315362192],"iteration":256,"passed_time":0.3871021792,"remaining_time":1.119131981},
{"learn":[0.2304149591],"iteration":257,"passed_time":0.3898491661,"remaining_time":1.121194113},
{"learn":[0.2293019592],"iteration":258,"passed_time":0.3916646618,"remaining_time":1.12055411},
{"learn":[0.2281926252],"iteration":259,"passed_time":0.3938594069,"remaining_time":1.120984466},
{"learn":[0.2270892166],"iteration":260,"passed_time":0.3960628876,"remaining_time":1.12141944},
{"learn":[0.2259917043],"iteration":261,"passed_time":0.3982284602,"remaining_time":1.121727495},
{"learn":[0.2248888625],"iteration":262,"passed_time":0.4005788222,"remaining_time":1.12253457},
{"learn":[0.2238030026],"iteration":263,"passed_time":0.4029054894,"remaining_time":1.123251667},
{"learn":[0.2226788424],"iteration":264,"passed_time":0.4060051606,"remaining_time":1.126089785},
{"learn":[0.2216066757],"iteration":265,"passed_time":0.4076906857,"remaining_time":1.124981065},
{"learn":[0.2205294858],"iteration":266,"passed_time":0.4097365939,"remaining_time":1.124857391},
{"learn":[0.2194552639],"iteration":267,"passed_time":0.4117921748,"remaining_time":1.124745791},
{"learn":[0.2184002205],"iteration":268,"passed_time":0.4134495055,"remaining_time":1.123537504},
{"learn":[0.2173484509],"iteration":269,"passed_time":0.4155560638,"remaining_time":1.123540469},
{"learn":[0.2163023225],"iteration":270,"passed_time":0.4178089098,"remaining_time":1.123921385},
{"learn":[0.2152618078],"iteration":271,"passed_time":0.4211311807,"remaining_time":1.127145219},
{"learn":[0.2142048107],"iteration":272,"passed_time":0.4232552522,"remaining_time":1.127130287},
{"learn":[0.2131753345],"iteration":273,"passed_time":0.4253821047,"remaining_time":1.127107328},
{"learn":[0.2121095932],"iteration":274,"passed_time":0.4274890631,"remaining_time":1.127016621},
{"learn":[0.2110495777],"iteration":275,"passed_time":0.4301163998,"remaining_time":1.128276353},
{"learn":[0.2100362048],"iteration":276,"passed_time":0.432216296,"remaining_time":1.128131343},
{"learn":[0.2090281504],"iteration":277,"passed_time":0.4349450293,"remaining_time":1.129605436},
{"learn":[0.2079994264],"iteration":278,"passed_time":0.4375903882,"remaining_time":1.130833942},
{"learn":[0.2069607985],"iteration":279,"passed_time":0.439778922,"remaining_time":1.130860085},
{"learn":[0.2059687218],"iteration":280,"passed_time":0.4414370384,"remaining_time":1.129513276},
{"learn":[0.2049819884],"iteration":281,"passed_time":0.443485316,"remaining_time":1.129157649},
{"learn":[0.203959198],"iteration":282,"passed_time":0.4455688142,"remaining_time":1.128879293},
{"learn":[0.2029576145],"iteration":283,"passed_time":0.4477167662,"remaining_time":1.12875072},
{"learn":[0.201974295],"iteration":284,"passed_time":0.4513033056,"remaining_time":1.132217065},
{"learn":[0.2010082903],"iteration":285,"passed_time":0.4533669881,"remaining_time":1.131832271},
{"learn":[0.2000474991],"iteration":286,"passed_time":0.4551416072,"remaining_time":1.130717651},
{"learn":[0.1990501141],"iteration":287,"passed_time":0.4572877999,"remaining_time":1.130517061},
{"learn":[0.1980994651],"iteration":288,"passed_time":0.4589886687,"remaining_time":1.129207417},
{"learn":[0.1971123889],"iteration":289,"passed_time":0.4612580292,"remaining_time":1.129286899},
{"learn":[0.1961346243],"iteration":290,"passed_time":0.4633687909,"remaining_time":1.128963824},
{"learn":[0.1951539347],"iteration":291,"passed_time":0.4668559562,"remaining_time":1.131965812},
{"learn":[0.1941977682],"iteration":292,"passed_time":0.4690047703,"remaining_time":1.131694104},
{"learn":[0.1932272748],"iteration":293,"passed_time":0.4711950619,"remaining_time":1.13150923},
{"learn":[0.1922660382],"iteration":294,"passed_time":0.4733638689,"remaining_time":1.131259415},
{"learn":[0.191309988],"iteration":295,"passed_time":0.4755918422,"remaining_time":1.131137354},
{"learn":[0.1903984056],"iteration":296,"passed_time":0.4779402606,"remaining_time":1.131286206},
{"learn":[0.1894522464],"iteration":297,"passed_time":0.4812626611,"remaining_time":1.133712712},
{"learn":[0.1884918013],"iteration":298,"passed_time":0.4834355922,"remaining_time":1.133405853},
{"learn":[0.1875944052],"iteration":299,"passed_time":0.4850807293,"remaining_time":1.131855035},
{"learn":[0.1867004096],"iteration":300,"passed_time":0.4867080259,"remaining_time":1.13026216},
{"learn":[0.1857734664],"iteration":301,"passed_time":0.4887747555,"remaining_time":1.1296847},
{"learn":[0.1848515279],"iteration":302,"passed_time":0.4908891152,"remaining_time":1.129206974},
{"learn":[0.1839345667],"iteration":303,"passed_time":0.4930088526,"remaining_time":1.128730794},
{"learn":[0.1830221364],"iteration":304,"passed_time":0.4962959597,"remaining_time":1.130903908},
{"learn":[0.1821150113],"iteration":305,"passed_time":0.4984970998,"remaining_time":1.13057839},
{"learn":[0.1812529736],"iteration":306,"passed_time":0.5002875254,"remaining_time":1.129313535},
{"learn":[0.1803927131],"iteration":307,"passed_time":0.5020089519,"remaining_time":1.127890243},
{"learn":[0.1794939818],"iteration":308,"passed_time":0.5041327462,"remaining_time":1.127364814},
{"learn":[0.178605484],"iteration":309,"passed_time":0.5062513254,"remaining_time":1.126817466},
{"learn":[0.1777217865],"iteration":310,"passed_time":0.5083702681,"remaining_time":1.126260819},
{"learn":[0.1768824555],"iteration":311,"passed_time":0.5106072332,"remaining_time":1.125954412},
{"learn":[0.1760079509],"iteration":312,"passed_time":0.5130095668,"remaining_time":1.125998634},
{"learn":[0.1751323014],"iteration":313,"passed_time":0.5152248927,"remaining_time":1.125618715},
{"learn":[0.1742619132],"iteration":314,"passed_time":0.5175898562,"remaining_time":1.125552544},
{"learn":[0.1733941777],"iteration":315,"passed_time":0.5197956305,"remaining_time":1.125127251},
{"learn":[0.1725109762],"iteration":316,"passed_time":0.522036639,"remaining_time":1.124766638},
{"learn":[0.1716539507],"iteration":317,"passed_time":0.5244308227,"remaining_time":1.124722708},
{"learn":[0.1708008828],"iteration":318,"passed_time":0.527426125,"remaining_time":1.125947308},
{"learn":[0.1699538333],"iteration":319,"passed_time":0.5296006808,"remaining_time":1.125401447},
{"learn":[0.1691097011],"iteration":320,"passed_time":0.5317040529,"remaining_time":1.124694866},
{"learn":[0.1682913758],"iteration":321,"passed_time":0.5338514898,"remaining_time":1.124072391},
{"learn":[0.1674618521],"iteration":322,"passed_time":0.5360203244,"remaining_time":1.123485324},
{"learn":[0.1666305808],"iteration":323,"passed_time":0.5393468584,"remaining_time":1.125303939},
{"learn":[0.1658036699],"iteration":324,"passed_time":0.5446583088,"remaining_time":1.131213411},
{"learn":[0.1649802592],"iteration":325,"passed_time":0.5472652203,"remaining_time":1.131462449},
{"learn":[0.1641638549],"iteration":326,"passed_time":0.5494072844,"remaining_time":1.130737316},
{"learn":[0.1633307236],"iteration":327,"passed_time":0.5514964596,"remaining_time":1.129895186},
{"learn":[0.1625209961],"iteration":328,"passed_time":0.554025829,"remaining_time":1.129943256},
{"learn":[0.1617155188],"iteration":329,"passed_time":0.5570403842,"remaining_time":1.13096078},
{"learn":[0.1608952432],"iteration":330,"passed_time":0.5592326133,"remaining_time":1.130291898},
{"learn":[0.1600973845],"iteration":331,"passed_time":0.5612873798,"remaining_time":1.129337258},
{"learn":[0.1593044806],"iteration":332,"passed_time":0.5633090465,"remaining_time":1.128309712},
{"learn":[0.1585157411],"iteration":333,"passed_time":0.5654056009,"remaining_time":1.127425539},
{"learn":[0.1577373798],"iteration":334,"passed_time":0.5676600912,"remaining_time":1.126847644},
{"learn":[0.1569568999],"iteration":335,"passed_time":0.5697425335,"remaining_time":1.125919769},
{"learn":[0.1561805214],"iteration":336,"passed_time":0.5727558676,"remaining_time":1.12681644},
{"learn":[0.1554082234],"iteration":337,"passed_time":0.574829649,"remaining_time":1.125849786},
{"learn":[0.1546399856],"iteration":338,"passed_time":0.5768998776,"remaining_time":1.124869673},
{"learn":[0.1538751398],"iteration":339,"passed_time":0.5790625798,"remaining_time":1.124062655},
{"learn":[0.1531141513],"iteration":340,"passed_time":0.581227947,"remaining_time":1.123252836},
{"learn":[0.1523572996],"iteration":341,"passed_time":0.5833400789,"remaining_time":1.122332666},
{"learn":[0.1516045121],"iteration":342,"passed_time":0.5855958611,"remaining_time":1.121680702},
{"learn":[0.1508561714],"iteration":343,"passed_time":0.5884831449,"remaining_time":1.122223672},
{"learn":[0.1501108199],"iteration":344,"passed_time":0.5905672521,"remaining_time":1.121221884},
{"learn":[0.1493506376],"iteration":345,"passed_time":0.592685881,"remaining_time":1.120279093},
{"learn":[0.1486138981],"iteration":346,"passed_time":0.5948557514,"remaining_time":1.119425953},
{"learn":[0.1478616517],"iteration":347,"passed_time":0.5970642927,"remaining_time":1.118637698},
{"learn":[0.1471390131],"iteration":348,"passed_time":0.5992536554,"remaining_time":1.117805529},
{"learn":[0.1464137843],"iteration":349,"passed_time":0.6020028761,"remaining_time":1.118005341},
{"learn":[0.1456731054],"iteration":350,"passed_time":0.6044378043,"remaining_time":1.117607222},
{"learn":[0.1449549129],"iteration":351,"passed_time":0.6067736747,"remaining_time":1.117015174},
{"learn":[0.1442410343],"iteration":352,"passed_time":0.6093173354,"remaining_time":1.116794096},
{"learn":[0.143530918],"iteration":353,"passed_time":0.6114544891,"remaining_time":1.115818079},
{"learn":[0.1428245452],"iteration":354,"passed_time":0.6137250807,"remaining_time":1.115077964},
{"learn":[0.1421026395],"iteration":355,"passed_time":0.6160344692,"remaining_time":1.114399433},
{"learn":[0.1413846464],"iteration":356,"passed_time":0.6189676138,"remaining_time":1.114835226},
{"learn":[0.140689292],"iteration":357,"passed_time":0.6211106403,"remaining_time":1.113835282},
{"learn":[0.1399788099],"iteration":358,"passed_time":0.6232436534,"remaining_time":1.112811091},
{"learn":[0.1392907257],"iteration":359,"passed_time":0.6253303533,"remaining_time":1.111698406},
{"learn":[0.1385876792],"iteration":360,"passed_time":0.6275860075,"remaining_time":1.110879387},
{"learn":[0.1379061477],"iteration":361,"passed_time":0.6297523979,"remaining_time":1.10989511},
{"learn":[0.1372104165],"iteration":362,"passed_time":0.6327177209,"remaining_time":1.110306304},
{"learn":[0.1365184606],"iteration":363,"passed_time":0.6348934923,"remaining_time":1.109319399},
{"learn":[0.1358482084],"iteration":364,"passed_time":0.6375875557,"remaining_time":1.109227665},
{"learn":[0.1351635022],"iteration":365,"passed_time":0.6400750575,"remaining_time":1.108763897},
{"learn":[0.1345002681],"iteration":366,"passed_time":0.6422412988,"remaining_time":1.107734992},
{"learn":[0.1337815902],"iteration":367,"passed_time":0.6440200476,"remaining_time":1.10603443},
{"learn":[0.1331074918],"iteration":368,"passed_time":0.6463003726,"remaining_time":1.105191152},
{"learn":[0.1324545521],"iteration":369,"passed_time":0.649254702,"remaining_time":1.105487736},
{"learn":[0.1318050638],"iteration":370,"passed_time":0.6516762416,"remaining_time":1.104863493},
{"learn":[0.1311590099],"iteration":371,"passed_time":0.6537453531,"remaining_time":1.103634628},
{"learn":[0.1304987386],"iteration":372,"passed_time":0.6557899781,"remaining_time":1.102360097},
{"learn":[0.1298594565],"iteration":373,"passed_time":0.6580035191,"remaining_time":1.101364179},
{"learn":[0.1291650987],"iteration":374,"passed_time":0.659712271,"remaining_time":1.099520452},
{"learn":[0.1285150619],"iteration":375,"passed_time":0.6621271114,"remaining_time":1.098849249},
{"learn":[0.127885708],"iteration":376,"passed_time":0.664685095,"remaining_time":1.098405343},
{"learn":[0.127259685],"iteration":377,"passed_time":0.6668306249,"remaining_time":1.097271557},
{"learn":[0.1266339287],"iteration":378,"passed_time":0.6688798073,"remaining_time":1.095974565},
{"learn":[0.1259567436],"iteration":379,"passed_time":0.6706294182,"remaining_time":1.09418484},
{"learn":[0.1253403762],"iteration":380,"passed_time":0.672740074,"remaining_time":1.092981905},
{"learn":[0.124727272],"iteration":381,"passed_time":0.6748285247,"remaining_time":1.091738294},
{"learn":[0.1241174147],"iteration":382,"passed_time":0.6778262621,"remaining_time":1.091955101},
{"learn":[0.1235107883],"iteration":383,"passed_time":0.6806985146,"remaining_time":1.091953867},
{"learn":[0.1228900444],"iteration":384,"passed_time":0.6830014388,"remaining_time":1.091028272},
{"learn":[0.1222897872],"iteration":385,"passed_time":0.685192717,"remaining_time":1.089917949},
{"learn":[0.1216755686],"iteration":386,"passed_time":0.6876009721,"remaining_time":1.089145726},
{"learn":[0.1210242596],"iteration":387,"passed_time":0.6893461491,"remaining_time":1.087319184},
{"learn":[0.1204333332],"iteration":388,"passed_time":0.6914185658,"remaining_time":1.086007053},
{"learn":[0.1198455408],"iteration":389,"passed_time":0.694806363,"remaining_time":1.086748414},
{"learn":[0.1192608668],"iteration":390,"passed_time":0.6970896653,"remaining_time":1.085748353},
{"learn":[0.1186792959],"iteration":391,"passed_time":0.6991057524,"remaining_time":1.084327289},
{"learn":[0.1180438996],"iteration":392,"passed_time":0.7012256746,"remaining_time":1.083063574},
{"learn":[0.1174683617],"iteration":393,"passed_time":0.7032970937,"remaining_time":1.081720911},
{"learn":[0.1168397728],"iteration":394,"passed_time":0.7050458405,"remaining_time":1.079880338},
{"learn":[0.1162702041],"iteration":395,"passed_time":0.7073178254,"remaining_time":1.078838299},
{"learn":[0.1157036594],"iteration":396,"passed_time":0.7106514916,"remaining_time":1.079402643},
{"learn":[0.1151230829],"iteration":397,"passed_time":0.712935771,"remaining_time":1.078360136},
{"learn":[0.1145624977],"iteration":398,"passed_time":0.7150057948,"remaining_time":1.076988678},
{"learn":[0.1139880354],"iteration":399,"passed_time":0.7170876466,"remaining_time":1.07563147},
{"learn":[0.1133777341],"iteration":400,"passed_time":0.7188545552,"remaining_time":1.073800196},
{"learn":[0.112809298],"iteration":401,"passed_time":0.7210357436,"remaining_time":1.072585509},
{"learn":[0.1122055856],"iteration":402,"passed_time":0.7244901701,"remaining_time":1.073252187},
{"learn":[0.1116431114],"iteration":403,"passed_time":0.7279716779,"remaining_time":1.073938416},
{"learn":[0.1110459126],"iteration":404,"passed_time":0.7302008829,"remaining_time":1.07276426},
{"learn":[0.110505356],"iteration":405,"passed_time":0.7327118926,"remaining_time":1.071997203},
{"learn":[0.1099676722],"iteration":406,"passed_time":0.7351547558,"remaining_time":1.071122285},
{"learn":[0.1094167453],"iteration":407,"passed_time":0.7387525137,"remaining_time":1.071915412},
{"learn":[0.1088314381],"iteration":408,"passed_time":0.7410268057,"remaining_time":1.070774675},
{"learn":[0.1082496952],"iteration":409,"passed_time":0.7428452576,"remaining_time":1.068972444},
{"learn":[0.1076714898],"iteration":410,"passed_time":0.7447010393,"remaining_time":1.067223631},
{"learn":[0.107147535],"iteration":411,"passed_time":0.747662317,"remaining_time":1.067052045},
{"learn":[0.1066263648],"iteration":412,"passed_time":0.7500933948,"remaining_time":1.066113372},
{"learn":[0.1061079654],"iteration":413,"passed_time":0.753003311,"remaining_time":1.065845266},
{"learn":[0.1055412113],"iteration":414,"passed_time":0.7553021387,"remaining_time":1.064703015},
{"learn":[0.1050277738],"iteration":415,"passed_time":0.7574354284,"remaining_time":1.063322813},
{"learn":[0.1044670714],"iteration":416,"passed_time":0.7591163308,"remaining_time":1.061306525},
{"learn":[0.1039097734],"iteration":417,"passed_time":0.7612839579,"remaining_time":1.05996953},
{"learn":[0.1033558543],"iteration":418,"passed_time":0.7630249259,"remaining_time":1.05803695},
{"learn":[0.1028052889],"iteration":419,"passed_time":0.7648325369,"remaining_time":1.056197313},
{"learn":[0.1022580524],"iteration":420,"passed_time":0.7665351212,"remaining_time":1.054213385},
{"learn":[0.1017604079],"iteration":421,"passed_time":0.7698344876,"remaining_time":1.054417853},
{"learn":[0.1012654072],"iteration":422,"passed_time":0.7725614762,"remaining_time":1.053824992},
{"learn":[0.1007730373],"iteration":423,"passed_time":0.7747891965,"remaining_time":1.052543814},
{"learn":[0.100236634],"iteration":424,"passed_time":0.776528705,"remaining_time":1.05059766},
{"learn":[0.09970347197],"iteration":425,"passed_time":0.7782131541,"remaining_time":1.048578287},
{"learn":[0.09921867195],"iteration":426,"passed_time":0.7803801074,"remaining_time":1.047207966},
{"learn":[0.09869118419],"iteration":427,"passed_time":0.7824538295,"remaining_time":1.045709324},
{"learn":[0.09816687775],"iteration":428,"passed_time":0.7848257213,"remaining_time":1.044604864},
{"learn":[0.09764572928],"iteration":429,"passed_time":0.7867905387,"remaining_time":1.0429549},
{"learn":[0.09717079676],"iteration":430,"passed_time":0.7890463797,"remaining_time":1.04168768},
{"learn":[0.09665518783],"iteration":431,"passed_time":0.7908078171,"remaining_time":1.039765834},
{"learn":[0.09614267872],"iteration":432,"passed_time":0.7929481289,"remaining_time":1.038340852},
{"learn":[0.09563324687],"iteration":433,"passed_time":0.7947024629,"remaining_time":1.036409203},
{"learn":[0.09512686993],"iteration":434,"passed_time":0.7968295348,"remaining_time":1.034962499},
{"learn":[0.0946235258],"iteration":435,"passed_time":0.7996317649,"remaining_time":1.034386044},
{"learn":[0.09416693368],"iteration":436,"passed_time":0.8018737328,"remaining_time":1.033077601},
{"learn":[0.09366899692],"iteration":437,"passed_time":0.8036761211,"remaining_time":1.031200868},
{"learn":[0.09317403652],"iteration":438,"passed_time":0.8054230433,"remaining_time":1.029253593},
{"learn":[0.09272032582],"iteration":439,"passed_time":0.8075694353,"remaining_time":1.027815645},
{"learn":[0.09226902506],"iteration":440,"passed_time":0.8099161396,"remaining_time":1.026628395},
{"learn":[0.09178159334],"iteration":441,"passed_time":0.8122751475,"remaining_time":1.025451431},
{"learn":[0.09129707259],"iteration":442,"passed_time":0.815165367,"remaining_time":1.024937042},
{"learn":[0.090815442],"iteration":443,"passed_time":0.8171324498,"remaining_time":1.023255951},
{"learn":[0.090336681],"iteration":444,"passed_time":0.8188336329,"remaining_time":1.021241947},
{"learn":[0.08986076921],"iteration":445,"passed_time":0.8206120964,"remaining_time":1.01932534},
{"learn":[0.08942308937],"iteration":446,"passed_time":0.8228799241,"remaining_time":1.018014761},
{"learn":[0.08895221632],"iteration":447,"passed_time":0.8247625135,"remaining_time":1.01622524},
{"learn":[0.08848414133],"iteration":448,"passed_time":0.8265713179,"remaining_time":1.014344758},
{"learn":[0.08805317075],"iteration":449,"passed_time":0.8294950178,"remaining_time":1.013827244},
{"learn":[0.08759004933],"iteration":450,"passed_time":0.8312639689,"remaining_time":1.01189339},
{"learn":[0.08716764678],"iteration":451,"passed_time":0.8334001857,"remaining_time":1.010405535},
{"learn":[0.08670948697],"iteration":452,"passed_time":0.8352505002,"remaining_time":1.008569589},
{"learn":[0.08625404415],"iteration":453,"passed_time":0.8369849934,"remaining_time":1.006594287},
{"learn":[0.08580129931],"iteration":454,"passed_time":0.8387005064,"remaining_time":1.00459731},
{"learn":[0.08538776655],"iteration":455,"passed_time":0.8407576864,"remaining_time":1.00300917},
{"learn":[0.08493986701],"iteration":456,"passed_time":0.8425594346,"remaining_time":1.001115477},
{"learn":[0.08449461658],"iteration":457,"passed_time":0.8451357486,"remaining_time":1.000138812},
{"learn":[0.0840519969],"iteration":458,"passed_time":0.8474188913,"remaining_time":0.9988096301},
{"learn":[0.08361198976],"iteration":459,"passed_time":0.8492505179,"remaining_time":0.9969462601},
{"learn":[0.08317457714],"iteration":460,"passed_time":0.8509653591,"remaining_time":0.9949464827},
{"learn":[0.08273974122],"iteration":461,"passed_time":0.852795866,"remaining_time":0.9930826318},
{"learn":[0.0823074643],"iteration":462,"passed_time":0.8546660063,"remaining_time":0.9912648928},
{"learn":[0.08187772891],"iteration":463,"passed_time":0.8567792372,"remaining_time":0.9897277396},
{"learn":[0.0814505177],"iteration":464,"passed_time":0.8593555001,"remaining_time":0.9887208442},
{"learn":[0.08105821096],"iteration":465,"passed_time":0.861551891,"remaining_time":0.9872719094},
{"learn":[0.080662031],"iteration":466,"passed_time":0.8637519827,"remaining_time":0.9858239974},
{"learn":[0.08024137747],"iteration":467,"passed_time":0.8654636362,"remaining_time":0.9838176378},
{"learn":[0.0798231934],"iteration":468,"passed_time":0.8672306151,"remaining_time":0.9818751741},
{"learn":[0.07940746206],"iteration":469,"passed_time":0.8693106836,"remaining_time":0.9802865155},
{"learn":[0.07899416689],"iteration":470,"passed_time":0.871096699,"remaining_time":0.9783655069},
{"learn":[0.07858329146],"iteration":471,"passed_time":0.8728429118,"remaining_time":0.9764005454},
{"learn":[0.07817481954],"iteration":472,"passed_time":0.8753541997,"remaining_time":0.9752889286},
{"learn":[0.077768735],"iteration":473,"passed_time":0.8773437402,"remaining_time":0.9735924205},
{"learn":[0.07736502191],"iteration":474,"passed_time":0.8790739631,"remaining_time":0.9716080645},
{"learn":[0.07696366444],"iteration":475,"passed_time":0.8809286393,"remaining_time":0.9697617794},
{"learn":[0.07656464696],"iteration":476,"passed_time":0.882751139,"remaining_time":0.9678801797},
{"learn":[0.07619636306],"iteration":477,"passed_time":0.8845351601,"remaining_time":0.9659568066},
{"learn":[0.07580159786],"iteration":478,"passed_time":0.8862713448,"remaining_time":0.9639819847},
{"learn":[0.07543722577],"iteration":479,"passed_time":0.888071663,"remaining_time":0.9620776349},
{"learn":[0.07504666762],"iteration":480,"passed_time":0.8904453121,"remaining_time":0.960792343},
{"learn":[0.07465838386],"iteration":481,"passed_time":0.8921688021,"remaining_time":0.9588038164},
{"learn":[0.07427235954],"iteration":482,"passed_time":0.8938546194,"remaining_time":0.9567760626},
{"learn":[0.07388857982],"iteration":483,"passed_time":0.8959720534,"remaining_time":0.9552098751},
{"learn":[0.07350702999],"iteration":484,"passed_time":0.897901725,"remaining_time":0.9534420379},
{"learn":[0.07312769548],"iteration":485,"passed_time":0.8997115457,"remaining_time":0.9515467787},
{"learn":[0.07275056187],"iteration":486,"passed_time":0.9015932218,"remaining_time":0.9497275622},
{"learn":[0.07237561485],"iteration":487,"passed_time":0.9040996219,"remaining_time":0.9485635377},
{"learn":[0.07200284024],"iteration":488,"passed_time":0.9065816223,"remaining_time":0.9473685256},
{"learn":[0.07163222399],"iteration":489,"passed_time":0.9084614327,"remaining_time":0.9455414912},
{"learn":[0.07126375219],"iteration":490,"passed_time":0.9110676584,"remaining_time":0.9444672874},
{"learn":[0.07089741102],"iteration":491,"passed_time":0.913515095,"remaining_time":0.9432229029},
{"learn":[0.07053318681],"iteration":492,"passed_time":0.9161684913,"remaining_time":0.9421854464},
{"learn":[0.07017106602],"iteration":493,"passed_time":0.9184253509,"remaining_time":0.9407352785},
{"learn":[0.06981103519],"iteration":494,"passed_time":0.9207105185,"remaining_time":0.939310731},
{"learn":[0.06945308102],"iteration":495,"passed_time":0.9225134054,"remaining_time":0.9373926538},
{"learn":[0.06909719029],"iteration":496,"passed_time":0.9246054676,"remaining_time":0.9357677066},
{"learn":[0.06874334993],"iteration":497,"passed_time":0.9266866245,"remaining_time":0.9341298906},
{"learn":[0.06839154696],"iteration":498,"passed_time":0.9284180138,"remaining_time":0.9321391281},
{"learn":[0.06804176852],"iteration":499,"passed_time":0.9301239401,"remaining_time":0.9301239401},
{"learn":[0.06769400186],"iteration":500,"passed_time":0.931826666,"remaining_time":0.9281067991},
{"learn":[0.06734823435],"iteration":501,"passed_time":0.9344653211,"remaining_time":0.9270193823},
{"learn":[0.06700445344],"iteration":502,"passed_time":0.936214929,"remaining_time":0.9250473553},
{"learn":[0.06666264671],"iteration":503,"passed_time":0.9379971738,"remaining_time":0.9231083297},
{"learn":[0.06632280185],"iteration":504,"passed_time":0.9397369363,"remaining_time":0.9211282841},
{"learn":[0.06598490663],"iteration":505,"passed_time":0.9415066817,"remaining_time":0.91917846},
{"learn":[0.06564894896],"iteration":506,"passed_time":0.9432938855,"remaining_time":0.9172463226},
{"learn":[0.06531491682],"iteration":507,"passed_time":0.9450315343,"remaining_time":0.9152667616},
{"learn":[0.0649827983],"iteration":508,"passed_time":0.946728888,"remaining_time":0.9132492809},
{"learn":[0.06465258159],"iteration":509,"passed_time":0.9494860125,"remaining_time":0.9122512669},
{"learn":[0.06432425498],"iteration":510,"passed_time":0.9513250447,"remaining_time":0.9103678021},
{"learn":[0.06399780687],"iteration":511,"passed_time":0.9530677932,"remaining_time":0.9083927404},
{"learn":[0.06367322573],"iteration":512,"passed_time":0.9548838537,"remaining_time":0.9064881808},
{"learn":[0.06335050014],"iteration":513,"passed_time":0.9566572181,"remaining_time":0.9045435953},
{"learn":[0.06302961878],"iteration":514,"passed_time":0.9583620161,"remaining_time":0.9025351025},
{"learn":[0.06271057041],"iteration":515,"passed_time":0.9600967423,"remaining_time":0.900555859},
{"learn":[0.06239334388],"iteration":516,"passed_time":0.9618605541,"remaining_time":0.8986047343},
{"learn":[0.06207792816],"iteration":517,"passed_time":0.9644470775,"remaining_time":0.8974198675},
{"learn":[0.06176431226],"iteration":518,"passed_time":0.9663346933,"remaining_time":0.8955818641},
{"learn":[0.06145248533],"iteration":519,"passed_time":0.9680331294,"remaining_time":0.8935690425},
{"learn":[0.06114243658],"iteration":520,"passed_time":0.9697791665,"remaining_time":0.8916011915},
{"learn":[0.0608341553],"iteration":521,"passed_time":0.9715458231,"remaining_time":0.8896530717},
{"learn":[0.06052763089],"iteration":522,"passed_time":0.9732842571,"remaining_time":0.8876799056},
{"learn":[0.06022285282],"iteration":523,"passed_time":0.975059546,"remaining_time":0.8857411143},
{"learn":[0.05991981064],"iteration":524,"passed_time":0.9767710991,"remaining_time":0.8837452801},
{"learn":[0.059618494],"iteration":525,"passed_time":0.9794223163,"remaining_time":0.8825972964},
{"learn":[0.0593188926],"iteration":526,"passed_time":0.9812636843,"remaining_time":0.8807167413},
{"learn":[0.05902099627],"iteration":527,"passed_time":0.9830056424,"remaining_time":0.8787474682},
{"learn":[0.05872479487],"iteration":528,"passed_time":0.9847078131,"remaining_time":0.8767436294},
{"learn":[0.05843027837],"iteration":529,"passed_time":0.9864315863,"remaining_time":0.874760086},
{"learn":[0.05813743682],"iteration":530,"passed_time":0.9881625624,"remaining_time":0.8727838828},
{"learn":[0.05784626032],"iteration":531,"passed_time":0.9898654656,"remaining_time":0.8707839058},
{"learn":[0.05755673908],"iteration":532,"passed_time":0.9916961246,"remaining_time":0.8688969797},
{"learn":[0.05726886337],"iteration":533,"passed_time":0.9939160702,"remaining_time":0.8673499789},
{"learn":[0.05698262352],"iteration":534,"passed_time":0.9959578323,"remaining_time":0.8656455925},
{"learn":[0.05669800997],"iteration":535,"passed_time":0.9978106336,"remaining_time":0.8637763694},
{"learn":[0.05641501321],"iteration":536,"passed_time":0.9995788497,"remaining_time":0.8618342782},
{"learn":[0.0561336238],"iteration":537,"passed_time":1.001271737,"remaining_time":0.8598281462},
{"learn":[0.05585183472],"iteration":538,"passed_time":1.003470826,"remaining_time":0.8582561243},
{"learn":[0.05557349934],"iteration":539,"passed_time":1.005268646,"remaining_time":0.8563399579},
{"learn":[0.05529674445],"iteration":540,"passed_time":1.007067527,"remaining_time":0.8544251296},
{"learn":[0.05502156091],"iteration":541,"passed_time":1.009753055,"remaining_time":0.8532599612},
{"learn":[0.0547479396],"iteration":542,"passed_time":1.011525282,"remaining_time":0.8513205414},
{"learn":[0.05447587151],"iteration":543,"passed_time":1.013275714,"remaining_time":0.8493634662},
{"learn":[0.05420534766],"iteration":544,"passed_time":1.01503315,"remaining_time":0.8474129967},
{"learn":[0.05393635916],"iteration":545,"passed_time":1.016736966,"remaining_time":0.8454186497},
{"learn":[0.05366889719],"iteration":546,"passed_time":1.018431521,"remaining_time":0.8434176946},
{"learn":[0.05340295298],"iteration":547,"passed_time":1.020206793,"remaining_time":0.8414844353},
{"learn":[0.05313851784],"iteration":548,"passed_time":1.022038102,"remaining_time":0.8395977855},
{"learn":[0.05287558313],"iteration":549,"passed_time":1.02497683,"remaining_time":0.8386174061},
{"learn":[0.05261414028],"iteration":550,"passed_time":1.026954361,"remaining_time":0.836846657},
{"learn":[0.05235418079],"iteration":551,"passed_time":1.028787148,"remaining_time":0.8349576851},
{"learn":[0.05209569621],"iteration":552,"passed_time":1.030665079,"remaining_time":0.8331054073},
{"learn":[0.05182412934],"iteration":553,"passed_time":1.032889002,"remaining_time":0.8315315791},
{"learn":[0.05155410133],"iteration":554,"passed_time":1.035047696,"remaining_time":0.8299031079},
{"learn":[0.05129963771],"iteration":555,"passed_time":1.036915993,"remaining_time":0.8280408286},
{"learn":[0.05103240735],"iteration":556,"passed_time":1.0400449,"remaining_time":0.8271811327},
{"learn":[0.05076669081],"iteration":557,"passed_time":1.042323261,"remaining_time":0.8256395726},
{"learn":[0.05050247902],"iteration":558,"passed_time":1.044463397,"remaining_time":0.8239863292},
{"learn":[0.050239763],"iteration":559,"passed_time":1.047310509,"remaining_time":0.8228868282},
{"learn":[0.04999175069],"iteration":560,"passed_time":1.049134148,"remaining_time":0.8209801974},
{"learn":[0.04973175831],"iteration":561,"passed_time":1.051258024,"remaining_time":0.8193078547},
{"learn":[0.0494863824],"iteration":562,"passed_time":1.053307505,"remaining_time":0.8175761627},
{"learn":[0.04922908592],"iteration":563,"passed_time":1.056766378,"remaining_time":0.8169328739},
{"learn":[0.04897324569],"iteration":564,"passed_time":1.059317749,"remaining_time":0.8155809217},
{"learn":[0.04873169073],"iteration":565,"passed_time":1.061358067,"remaining_time":0.813832864},
{"learn":[0.04847850429],"iteration":566,"passed_time":1.063480403,"remaining_time":0.8121464098},
{"learn":[0.04822675046],"iteration":567,"passed_time":1.065663939,"remaining_time":0.8105049679},
{"learn":[0.04799044506],"iteration":568,"passed_time":1.067992496,"remaining_time":0.8089714687},
{"learn":[0.04774133342],"iteration":569,"passed_time":1.07112764,"remaining_time":0.8080436579},
{"learn":[0.04751523684],"iteration":570,"passed_time":1.072870596,"remaining_time":0.8060621468},
{"learn":[0.04726864521],"iteration":571,"passed_time":1.075046486,"remaining_time":0.8044054124},
{"learn":[0.04704488457],"iteration":572,"passed_time":1.076756117,"remaining_time":0.8023994099},
{"learn":[0.04682234308],"iteration":573,"passed_time":1.07921167,"remaining_time":0.8009480335},
{"learn":[0.04659169351],"iteration":574,"passed_time":1.081418586,"remaining_time":0.7993093897},
{"learn":[0.04636374898],"iteration":575,"passed_time":1.084305021,"remaining_time":0.7981689737},
{"learn":[0.04613704242],"iteration":576,"passed_time":1.087028878,"remaining_time":0.7969033195},
{"learn":[0.04591156722],"iteration":577,"passed_time":1.089629106,"remaining_time":0.7955423578},
{"learn":[0.04568732047],"iteration":578,"passed_time":1.092110349,"remaining_time":0.7940905995},
{"learn":[0.04546427959],"iteration":579,"passed_time":1.095034586,"remaining_time":0.7929560792},
{"learn":[0.04524245035],"iteration":580,"passed_time":1.098587981,"remaining_time":0.7922691292},
{"learn":[0.04502182631],"iteration":581,"passed_time":1.102014343,"remaining_time":0.7914810914},
{"learn":[0.04480240108],"iteration":582,"passed_time":1.104489599,"remaining_time":0.7900037098},
{"learn":[0.04459124291],"iteration":583,"passed_time":1.106412656,"remaining_time":0.7881295634},
{"learn":[0.04437410476],"iteration":584,"passed_time":1.10890898,"remaining_time":0.7866619258},
{"learn":[0.04415814723],"iteration":585,"passed_time":1.111420506,"remaining_time":0.7852015176},
{"learn":[0.04395031692],"iteration":586,"passed_time":1.113824398,"remaining_time":0.7836617997},
{"learn":[0.04373661151],"iteration":587,"passed_time":1.116635842,"remaining_time":0.7824047059},
{"learn":[0.04352406886],"iteration":588,"passed_time":1.119119777,"remaining_time":0.7809138005},
{"learn":[0.04331266123],"iteration":589,"passed_time":1.121467827,"remaining_time":0.7793250999},
{"learn":[0.04310919129],"iteration":590,"passed_time":1.123643396,"remaining_time":0.777614465},
{"learn":[0.04290000118],"iteration":591,"passed_time":1.126598057,"remaining_time":0.7764392018},
{"learn":[0.04269195014],"iteration":592,"passed_time":1.130530212,"remaining_time":0.77592883},
{"learn":[0.04249169245],"iteration":593,"passed_time":1.132481101,"remaining_time":0.7740527387},
{"learn":[0.04228581392],"iteration":594,"passed_time":1.134982186,"remaining_time":0.7725508994},
{"learn":[0.04208105731],"iteration":595,"passed_time":1.137496733,"remaining_time":0.7710548321},
{"learn":[0.04187741676],"iteration":596,"passed_time":1.140235132,"remaining_time":0.7697064629},
{"learn":[0.0416748658],"iteration":597,"passed_time":1.143031259,"remaining_time":0.7683922511},
{"learn":[0.04147341903],"iteration":598,"passed_time":1.148879653,"remaining_time":0.7691164287},
{"learn":[0.04127306921],"iteration":599,"passed_time":1.152427077,"remaining_time":0.7682847181},
{"learn":[0.04107380219],"iteration":600,"passed_time":1.154705988,"remaining_time":0.7666018122},
{"learn":[0.0408756205],"iteration":601,"passed_time":1.156938927,"remaining_time":0.7648865329},
{"learn":[0.04067852008],"iteration":602,"passed_time":1.159385738,"remaining_time":0.7633103451},
{"learn":[0.04048854993],"iteration":603,"passed_time":1.161772779,"remaining_time":0.7616920868},
{"learn":[0.04028060219],"iteration":604,"passed_time":1.163970213,"remaining_time":0.7599474941},
{"learn":[0.04007386464],"iteration":605,"passed_time":1.166524814,"remaining_time":0.758433625},
{"learn":[0.03988087859],"iteration":606,"passed_time":1.168853523,"remaining_time":0.7567700732},
{"learn":[0.03967636152],"iteration":607,"passed_time":1.171412997,"remaining_time":0.7552531168},
{"learn":[0.03948543197],"iteration":608,"passed_time":1.173987611,"remaining_time":0.753742456},
{"learn":[0.03928311153],"iteration":609,"passed_time":1.177608386,"remaining_time":0.7528971651},
{"learn":[0.03908196744],"iteration":610,"passed_time":1.180181614,"remaining_time":0.7513758555},
{"learn":[0.0388940762],"iteration":611,"passed_time":1.182951127,"remaining_time":0.7499755512},
{"learn":[0.03869509253],"iteration":612,"passed_time":1.185372126,"remaining_time":0.7483507546},
{"learn":[0.03851466112],"iteration":613,"passed_time":1.18740765,"remaining_time":0.7464810306},
{"learn":[0.03831774124],"iteration":614,"passed_time":1.191831919,"remaining_time":0.7461061607},
{"learn":[0.03813377641],"iteration":615,"passed_time":1.194494893,"remaining_time":0.7446201928},
{"learn":[0.03793897312],"iteration":616,"passed_time":1.197277445,"remaining_time":0.7432046374},
{"learn":[0.03774530224],"iteration":617,"passed_time":1.199929155,"remaining_time":0.7417037818},
{"learn":[0.0375642706],"iteration":618,"passed_time":1.202642919,"remaining_time":0.7402374022},
{"learn":[0.03735825202],"iteration":619,"passed_time":1.206004518,"remaining_time":0.7391640591},
{"learn":[0.03715351871],"iteration":620,"passed_time":1.208834511,"remaining_time":0.7377589046},
{"learn":[0.03695006078],"iteration":621,"passed_time":1.211007916,"remaining_time":0.7359501485},
{"learn":[0.03677761659],"iteration":622,"passed_time":1.21272048,"remaining_time":0.7338613499},
{"learn":[0.03657623794],"iteration":623,"passed_time":1.214911682,"remaining_time":0.7320621676},
{"learn":[0.03640555723],"iteration":624,"passed_time":1.21667781,"remaining_time":0.7300066859},
{"learn":[0.0362062367],"iteration":625,"passed_time":1.219101073,"remaining_time":0.7283447306},
{"learn":[0.03603730142],"iteration":626,"passed_time":1.222190974,"remaining_time":0.727076927},
{"learn":[0.03586432009],"iteration":627,"passed_time":1.224681426,"remaining_time":0.7254482331},
{"learn":[0.03566789385],"iteration":628,"passed_time":1.226827501,"remaining_time":0.7236136773},
{"learn":[0.03550155482],"iteration":629,"passed_time":1.228549631,"remaining_time":0.7215291486},
{"learn":[0.03533123447],"iteration":630,"passed_time":1.230775773,"remaining_time":0.7197405076},
{"learn":[0.03516667674],"iteration":631,"passed_time":1.232552563,"remaining_time":0.717688834},
{"learn":[0.03498726145],"iteration":632,"passed_time":1.235404716,"remaining_time":0.7162615019},
{"learn":[0.03480888948],"iteration":633,"passed_time":1.238839813,"remaining_time":0.715166201},
{"learn":[0.03463155422],"iteration":634,"passed_time":1.24118837,"remaining_time":0.7134389845},
{"learn":[0.03446567978],"iteration":635,"passed_time":1.24347465,"remaining_time":0.7116741707},
{"learn":[0.03427660883],"iteration":636,"passed_time":1.2456832,"remaining_time":0.7098634246},
{"learn":[0.03408871901],"iteration":637,"passed_time":1.247930762,"remaining_time":0.7080735673},
{"learn":[0.03390200122],"iteration":638,"passed_time":1.250404844,"remaining_time":0.7064102483},
{"learn":[0.03374390928],"iteration":639,"passed_time":1.25309596,"remaining_time":0.7048664776},
{"learn":[0.03358669357],"iteration":640,"passed_time":1.254778579,"remaining_time":0.7027543057},
{"learn":[0.03342580387],"iteration":641,"passed_time":1.2569059,"remaining_time":0.7008914521},
{"learn":[0.03324253361],"iteration":642,"passed_time":1.259064377,"remaining_time":0.6990450742},
{"learn":[0.03308773502],"iteration":643,"passed_time":1.260823273,"remaining_time":0.6969768405},
{"learn":[0.03292483363],"iteration":644,"passed_time":1.262643731,"remaining_time":0.6949434488},
{"learn":[0.03275719725],"iteration":645,"passed_time":1.264965433,"remaining_time":0.6931853918},
{"learn":[0.03260038704],"iteration":646,"passed_time":1.268283359,"remaining_time":0.6919691278},
{"learn":[0.03243455482],"iteration":647,"passed_time":1.270553273,"remaining_time":0.6901770864},
{"learn":[0.03226968618],"iteration":648,"passed_time":1.273018287,"remaining_time":0.6884890888},
{"learn":[0.03211538047],"iteration":649,"passed_time":1.275463709,"remaining_time":0.6867881512},
{"learn":[0.03195228697],"iteration":650,"passed_time":1.277912568,"remaining_time":0.6850867684},
{"learn":[0.03179014088],"iteration":651,"passed_time":1.281875215,"remaining_time":0.6841910658},
{"learn":[0.03162893629],"iteration":652,"passed_time":1.284517146,"remaining_time":0.6825841495},
{"learn":[0.03147790161],"iteration":653,"passed_time":1.286867953,"remaining_time":0.6808200487},
{"learn":[0.03130497531],"iteration":654,"passed_time":1.289080249,"remaining_time":0.6789811997},
{"learn":[0.03113313275],"iteration":655,"passed_time":1.291301594,"remaining_time":0.6771459578},
{"learn":[0.03096236551],"iteration":656,"passed_time":1.296374198,"remaining_time":0.6767980972},
{"learn":[0.03079266527],"iteration":657,"passed_time":1.299207092,"remaining_time":0.675271771},
{"learn":[0.03062402379],"iteration":658,"passed_time":1.301727988,"remaining_time":0.6735800364},
{"learn":[0.03045643292],"iteration":659,"passed_time":1.303854622,"remaining_time":0.671682684},
{"learn":[0.03031429507],"iteration":660,"passed_time":1.305608685,"remaining_time":0.6695935617},
{"learn":[0.03017294501],"iteration":661,"passed_time":1.307287645,"remaining_time":0.6674671058},
{"learn":[0.03000773574],"iteration":662,"passed_time":1.309543903,"remaining_time":0.6656354378},
{"learn":[0.02986783278],"iteration":663,"passed_time":1.312406694,"remaining_time":0.6641094112},
{"learn":[0.02970431343],"iteration":664,"passed_time":1.314594016,"remaining_time":0.6622390909},
{"learn":[0.02954181294],"iteration":665,"passed_time":1.316758977,"remaining_time":0.6603566042},
{"learn":[0.02940399611],"iteration":666,"passed_time":1.318494291,"remaining_time":0.6582587689},
{"learn":[0.02924315797],"iteration":667,"passed_time":1.320595668,"remaining_time":0.6563439549},
{"learn":[0.02908332056],"iteration":668,"passed_time":1.322941833,"remaining_time":0.654549696},
{"learn":[0.02894755937],"iteration":669,"passed_time":1.324864689,"remaining_time":0.6525452944},
{"learn":[0.02878935721],"iteration":670,"passed_time":1.327815749,"remaining_time":0.6510452776},
{"learn":[0.02865498599],"iteration":671,"passed_time":1.329428743,"remaining_time":0.648887839},
{"learn":[0.02851349421],"iteration":672,"passed_time":1.331050085,"remaining_time":0.6467360741},
{"learn":[0.02837689345],"iteration":673,"passed_time":1.333127283,"remaining_time":0.6448063714},
{"learn":[0.02824103822],"iteration":674,"passed_time":1.335224071,"remaining_time":0.6428856638},
{"learn":[0.02810592474],"iteration":675,"passed_time":1.337376821,"remaining_time":0.6409912576},
{"learn":[0.02797154926],"iteration":676,"passed_time":1.339720631,"remaining_time":0.6391872436},
{"learn":[0.02781836776],"iteration":677,"passed_time":1.342752329,"remaining_time":0.637708333},
{"learn":[0.0276661422],"iteration":678,"passed_time":1.34491298,"remaining_time":0.6358130581},
{"learn":[0.02753720352],"iteration":679,"passed_time":1.34661679,"remaining_time":0.6337020186},
{"learn":[0.02740898008],"iteration":680,"passed_time":1.348270406,"remaining_time":0.6315686632},
{"learn":[0.0272676199],"iteration":681,"passed_time":1.350335533,"remaining_time":0.6296285918},
{"learn":[0.02714072593],"iteration":682,"passed_time":1.352061344,"remaining_time":0.6275306675},
{"learn":[0.02700079408],"iteration":683,"passed_time":1.354382598,"remaining_time":0.6257089194},
{"learn":[0.02687521613],"iteration":684,"passed_time":1.356902167,"remaining_time":0.6239769087},
{"learn":[0.0267366985],"iteration":685,"passed_time":1.359066996,"remaining_time":0.6220802283},
{"learn":[0.02660478934],"iteration":686,"passed_time":1.360793685,"remaining_time":0.619983149},
{"learn":[0.02647778835],"iteration":687,"passed_time":1.362894755,"remaining_time":0.6180569237},
{"learn":[0.02635148218],"iteration":688,"passed_time":1.364995129,"remaining_time":0.6161298768},
{"learn":[0.02621825513],"iteration":689,"passed_time":1.367295346,"remaining_time":0.614292112},
{"learn":[0.02609330763],"iteration":690,"passed_time":1.369444739,"remaining_time":0.6123855635},
{"learn":[0.02597223929],"iteration":691,"passed_time":1.371883456,"remaining_time":0.6106070873},
{"learn":[0.02583851368],"iteration":692,"passed_time":1.374210662,"remaining_time":0.6087773064},
{"learn":[0.02571113921],"iteration":693,"passed_time":1.37590189,"remaining_time":0.6066656749},
{"learn":[0.02558133321],"iteration":694,"passed_time":1.377984801,"remaining_time":0.6047271428},
{"learn":[0.02545228125],"iteration":695,"passed_time":1.380044891,"remaining_time":0.6027782282},
{"learn":[0.02533119396],"iteration":696,"passed_time":1.38218657,"remaining_time":0.600864463},
{"learn":[0.0252035358],"iteration":697,"passed_time":1.384410527,"remaining_time":0.5989856433},
{"learn":[0.02507661916],"iteration":698,"passed_time":1.387941214,"remaining_time":0.5976685342},
{"learn":[0.02495747429],"iteration":699,"passed_time":1.390272855,"remaining_time":0.5958312235},
{"learn":[0.02484192111],"iteration":700,"passed_time":1.392013681,"remaining_time":0.5937405001},
{"learn":[0.02472252468],"iteration":701,"passed_time":1.394168313,"remaining_time":0.591826435},
{"learn":[0.02460074916],"iteration":702,"passed_time":1.396217073,"remaining_time":0.5898669567},
{"learn":[0.02447696546],"iteration":703,"passed_time":1.398604267,"remaining_time":0.5880495215},
{"learn":[0.02435390199],"iteration":704,"passed_time":1.401053198,"remaining_time":0.5862563027},
{"learn":[0.02423155431],"iteration":705,"passed_time":1.403730192,"remaining_time":0.584556199},
{"learn":[0.02411669031],"iteration":706,"passed_time":1.405818407,"remaining_time":0.5826093256},
{"learn":[0.02399566706],"iteration":707,"passed_time":1.407890974,"remaining_time":0.5806555993},
{"learn":[0.02387534781],"iteration":708,"passed_time":1.410050727,"remaining_time":0.5787373224},
{"learn":[0.02375572825],"iteration":709,"passed_time":1.412285891,"remaining_time":0.5768491669},
{"learn":[0.02364331534],"iteration":710,"passed_time":1.414574618,"remaining_time":0.5749818066},
{"learn":[0.02353417517],"iteration":711,"passed_time":1.416773367,"remaining_time":0.5730768675},
{"learn":[0.02342111734],"iteration":712,"passed_time":1.419159468,"remaining_time":0.571246518},
{"learn":[0.02330582584],"iteration":713,"passed_time":1.420847773,"remaining_time":0.5691351022},
{"learn":[0.02318916753],"iteration":714,"passed_time":1.422922776,"remaining_time":0.5671790087},
{"learn":[0.02307318886],"iteration":715,"passed_time":1.425223029,"remaining_time":0.5653119278},
{"learn":[0.0229578857],"iteration":716,"passed_time":1.427406923,"remaining_time":0.5633977115},
{"learn":[0.02284952058],"iteration":717,"passed_time":1.429567475,"remaining_time":0.5614735766},
{"learn":[0.02273546919],"iteration":718,"passed_time":1.432322332,"remaining_time":0.5597810504},
{"learn":[0.02262208226],"iteration":719,"passed_time":1.434643487,"remaining_time":0.5579169116},
{"learn":[0.02249705966],"iteration":720,"passed_time":1.436822015,"remaining_time":0.5559963136},
{"learn":[0.02237283324],"iteration":721,"passed_time":1.439032028,"remaining_time":0.5540871242},
{"learn":[0.0222493967],"iteration":722,"passed_time":1.441133377,"remaining_time":0.552135471},
{"learn":[0.02212674381],"iteration":723,"passed_time":1.443349323,"remaining_time":0.5502270899},
{"learn":[0.02202454003],"iteration":724,"passed_time":1.445116128,"remaining_time":0.5481474969},
{"learn":[0.02192290897],"iteration":725,"passed_time":1.447416779,"remaining_time":0.5462702446},
{"learn":[0.0218174917],"iteration":726,"passed_time":1.44980759,"remaining_time":0.5444256836},
{"learn":[0.0217169399],"iteration":727,"passed_time":1.4515565,"remaining_time":0.5423397913},
{"learn":[0.02161259937],"iteration":728,"passed_time":1.453751361,"remaining_time":0.5404206018},
{"learn":[0.02150621048],"iteration":729,"passed_time":1.455494004,"remaining_time":0.5383333986},
{"learn":[0.02140482553],"iteration":730,"passed_time":1.45761101,"remaining_time":0.5363848998},
{"learn":[0.02130399944],"iteration":731,"passed_time":1.459713077,"remaining_time":0.534430471},
{"learn":[0.02119922372],"iteration":732,"passed_time":1.461406575,"remaining_time":0.5323268152},
{"learn":[0.02109364043],"iteration":733,"passed_time":1.464324776,"remaining_time":0.5306681067},
{"learn":[0.02098867322],"iteration":734,"passed_time":1.466413461,"remaining_time":0.5287068941},
{"learn":[0.02087779148],"iteration":735,"passed_time":1.469432424,"remaining_time":0.5270790218},
{"learn":[0.02076759632],"iteration":736,"passed_time":1.472186683,"remaining_time":0.525352914},
{"learn":[0.0206580826],"iteration":737,"passed_time":1.474825599,"remaining_time":0.5235830716},
{"learn":[0.02054924528],"iteration":738,"passed_time":1.478027561,"remaining_time":0.522009734},
{"learn":[0.02045244714],"iteration":739,"passed_time":1.480409835,"remaining_time":0.5201439962},
{"learn":[0.02034475599],"iteration":740,"passed_time":1.482908475,"remaining_time":0.5183175371},
{"learn":[0.0202377292],"iteration":741,"passed_time":1.485587007,"remaining_time":0.5165518166},
{"learn":[0.02014239121],"iteration":742,"passed_time":1.487773699,"remaining_time":0.5146135137},
{"learn":[0.02003649184],"iteration":743,"passed_time":1.489947624,"remaining_time":0.5126701503},
{"learn":[0.01994212614],"iteration":744,"passed_time":1.493274623,"remaining_time":0.5111208442},
{"learn":[0.01983734264],"iteration":745,"passed_time":1.495622607,"remaining_time":0.5092334347},
{"learn":[0.01973320489],"iteration":746,"passed_time":1.497836337,"remaining_time":0.5072993215},
{"learn":[0.01964026368],"iteration":747,"passed_time":1.499941943,"remaining_time":0.5053280343},
{"learn":[0.01953722361],"iteration":748,"passed_time":1.50208932,"remaining_time":0.5033703862},
{"learn":[0.01944523089],"iteration":749,"passed_time":1.504483662,"remaining_time":0.5014945538},
{"learn":[0.01934327726],"iteration":750,"passed_time":1.507063325,"remaining_time":0.4996787855},
{"learn":[0.0192469069],"iteration":751,"passed_time":1.509838429,"remaining_time":0.4979254394},
{"learn":[0.01915630091],"iteration":752,"passed_time":1.512027586,"remaining_time":0.4959771764},
{"learn":[0.01906619604],"iteration":753,"passed_time":1.514163483,"remaining_time":0.4940108976},
{"learn":[0.01897123997],"iteration":754,"passed_time":1.516468351,"remaining_time":0.4920990012},
{"learn":[0.01888205509],"iteration":755,"passed_time":1.518891006,"remaining_time":0.4902240813},
{"learn":[0.0187880731],"iteration":756,"passed_time":1.521042674,"remaining_time":0.4882607264},
{"learn":[0.0186997998],"iteration":757,"passed_time":1.524275834,"remaining_time":0.4866421529},
{"learn":[0.01861037519],"iteration":758,"passed_time":1.52642947,"remaining_time":0.4846765512},
{"learn":[0.0185194194],"iteration":759,"passed_time":1.528101044,"remaining_time":0.4825582244},
{"learn":[0.01842727315],"iteration":760,"passed_time":1.530224758,"remaining_time":0.4805830712},
{"learn":[0.01834079357],"iteration":761,"passed_time":1.532361382,"remaining_time":0.4786115603},
{"learn":[0.01825479351],"iteration":762,"passed_time":1.534587082,"remaining_time":0.476667285},
{"learn":[0.01817148087],"iteration":763,"passed_time":1.536353846,"remaining_time":0.4745805073},
{"learn":[0.0180847488],"iteration":764,"passed_time":1.53952317,"remaining_time":0.4729254181},
{"learn":[0.01799650934],"iteration":765,"passed_time":1.541232296,"remaining_time":0.4708203096},
{"learn":[0.01790700883],"iteration":766,"passed_time":1.543291649,"remaining_time":0.4688226261},
{"learn":[0.01782317064],"iteration":767,"passed_time":1.545380062,"remaining_time":0.4668335604},
{"learn":[0.01773456135],"iteration":768,"passed_time":1.547571218,"remaining_time":0.4648750992},
{"learn":[0.01765159538],"iteration":769,"passed_time":1.549819593,"remaining_time":0.4629331253},
{"learn":[0.01756749166],"iteration":770,"passed_time":1.551971406,"remaining_time":0.4609616757},
{"learn":[0.01748761392],"iteration":771,"passed_time":1.554597638,"remaining_time":0.4591298723},
{"learn":[0.0174043723],"iteration":772,"passed_time":1.556720546,"remaining_time":0.4571482068},
{"learn":[0.01731960155],"iteration":773,"passed_time":1.558377685,"remaining_time":0.4550301767},
{"learn":[0.01723351085],"iteration":774,"passed_time":1.560437916,"remaining_time":0.4530303627},
{"learn":[0.0171479162],"iteration":775,"passed_time":1.562563255,"remaining_time":0.4510491871},
{"learn":[0.01706787456],"iteration":776,"passed_time":1.564849665,"remaining_time":0.4491138678},
{"learn":[0.01698313064],"iteration":777,"passed_time":1.567052645,"remaining_time":0.4471538395},
{"learn":[0.0168878926],"iteration":778,"passed_time":1.570379196,"remaining_time":0.4455119415},
{"learn":[0.01681126459],"iteration":779,"passed_time":1.572210461,"remaining_time":0.4434439763},
{"learn":[0.01673130834],"iteration":780,"passed_time":1.574563076,"remaining_time":0.4415228087},
{"learn":[0.01665550179],"iteration":781,"passed_time":1.576377996,"remaining_time":0.4394506434},
{"learn":[0.01657636493],"iteration":782,"passed_time":1.578770162,"remaining_time":0.4375391127},
{"learn":[0.01649577499],"iteration":783,"passed_time":1.580573248,"remaining_time":0.4354640581},
{"learn":[0.01641896969],"iteration":784,"passed_time":1.583251262,"remaining_time":0.4336293265},
{"learn":[0.01633748787],"iteration":785,"passed_time":1.586202564,"remaining_time":0.4318668558},
{"learn":[0.01626146629],"iteration":786,"passed_time":1.588428765,"remaining_time":0.4299051169},
{"learn":[0.01618249676],"iteration":787,"passed_time":1.59018235,"remaining_time":0.4278155561},
{"learn":[0.01610224012],"iteration":788,"passed_time":1.592429809,"remaining_time":0.4258589223},
{"learn":[0.01602735629],"iteration":789,"passed_time":1.594673064,"remaining_time":0.4239004346},
{"learn":[0.01595289109],"iteration":790,"passed_time":1.597061509,"remaining_time":0.4219795895},
{"learn":[0.01587380542],"iteration":791,"passed_time":1.600788783,"remaining_time":0.4204091752},
{"learn":[0.01580009988],"iteration":792,"passed_time":1.602945631,"remaining_time":0.4184233865},
{"learn":[0.01572345181],"iteration":793,"passed_time":1.604649653,"remaining_time":0.4163196834},
{"learn":[0.01564554469],"iteration":794,"passed_time":1.606790584,"remaining_time":0.4143296474},
{"learn":[0.01557294738],"iteration":795,"passed_time":1.608963553,"remaining_time":0.4123474434},
{"learn":[0.01550075662],"iteration":796,"passed_time":1.611206345,"remaining_time":0.4103825445},
{"learn":[0.01542744917],"iteration":797,"passed_time":1.614143346,"remaining_time":0.4085926766},
{"learn":[0.01535815787],"iteration":798,"passed_time":1.61614402,"remaining_time":0.4065643906},
{"learn":[0.01528560266],"iteration":799,"passed_time":1.618415652,"remaining_time":0.4046039131},
{"learn":[0.01521160404],"iteration":800,"passed_time":1.620119105,"remaining_time":0.4025015005},
{"learn":[0.01513626655],"iteration":801,"passed_time":1.622201145,"remaining_time":0.4004935494},
{"learn":[0.01506132833],"iteration":802,"passed_time":1.624363751,"remaining_time":0.3985051793},
{"learn":[0.01499168085],"iteration":803,"passed_time":1.626639749,"remaining_time":0.3965440185},
{"learn":[0.01492456763],"iteration":804,"passed_time":1.628735296,"remaining_time":0.3945383637},
{"learn":[0.01485417845],"iteration":805,"passed_time":1.631250359,"remaining_time":0.392633461},
{"learn":[0.01478241461],"iteration":806,"passed_time":1.632999572,"remaining_time":0.3905438877},
{"learn":[0.01470928631],"iteration":807,"passed_time":1.635182206,"remaining_time":0.388558148},
{"learn":[0.01464139123],"iteration":808,"passed_time":1.637362019,"remaining_time":0.3865712555},
{"learn":[0.01456899928],"iteration":809,"passed_time":1.639439075,"remaining_time":0.3845597831},
{"learn":[0.01450180587],"iteration":810,"passed_time":1.642026538,"remaining_time":0.3826670969},
{"learn":[0.0144335533],"iteration":811,"passed_time":1.645447361,"remaining_time":0.3809656451},
{"learn":[0.01436922071],"iteration":812,"passed_time":1.647288883,"remaining_time":0.378896705},
{"learn":[0.01430166919],"iteration":813,"passed_time":1.649452336,"remaining_time":0.376901885},
{"learn":[0.01423272607],"iteration":814,"passed_time":1.651154395,"remaining_time":0.3748019179},
{"learn":[0.0141623615],"iteration":815,"passed_time":1.653243034,"remaining_time":0.3727900958},
{"learn":[0.01409723527],"iteration":816,"passed_time":1.65653382,"remaining_time":0.371047355},
{"learn":[0.01403105758],"iteration":817,"passed_time":1.661824857,"remaining_time":0.3697458729},
{"learn":[0.01395104095],"iteration":818,"passed_time":1.663974292,"remaining_time":0.3677403503},
{"learn":[0.01387156438],"iteration":819,"passed_time":1.666087047,"remaining_time":0.3657264249},
{"learn":[0.01380981714],"iteration":820,"passed_time":1.667776416,"remaining_time":0.3636199494},
{"learn":[0.01373115512],"iteration":821,"passed_time":1.670240429,"remaining_time":0.3616822341},
{"learn":[0.01365302309],"iteration":822,"passed_time":1.67302752,"remaining_time":0.359812723},
{"learn":[0.01359218661],"iteration":823,"passed_time":1.675676533,"remaining_time":0.3579114925},
{"learn":[0.01353170188],"iteration":824,"passed_time":1.677366755,"remaining_time":0.3558050693},
{"learn":[0.01346815945],"iteration":825,"passed_time":1.679453898,"remaining_time":0.3537832665},
{"learn":[0.01340330673],"iteration":826,"passed_time":1.681109863,"remaining_time":0.3516711079},
{"learn":[0.01334167408],"iteration":827,"passed_time":1.683357654,"remaining_time":0.3496829908},
{"learn":[0.01328038974],"iteration":828,"passed_time":1.685544621,"remaining_time":0.3476817011},
{"learn":[0.01321813743],"iteration":829,"passed_time":1.687831401,"remaining_time":0.3457004075},
{"learn":[0.01314265838],"iteration":830,"passed_time":1.691080456,"remaining_time":0.3439140759},
{"learn":[0.01308434894],"iteration":831,"passed_time":1.692799811,"remaining_time":0.3418153464},
{"learn":[0.01302637782],"iteration":832,"passed_time":1.694514161,"remaining_time":0.3397165245},
{"learn":[0.01296537659],"iteration":833,"passed_time":1.696684549,"remaining_time":0.3377093945},
{"learn":[0.01290309989],"iteration":834,"passed_time":1.698594441,"remaining_time":0.3356503986},
{"learn":[0.01283939615],"iteration":835,"passed_time":1.700780172,"remaining_time":0.333645871},
{"learn":[0.01277607652],"iteration":836,"passed_time":1.702954994,"remaining_time":0.3316387861},
{"learn":[0.01271753801],"iteration":837,"passed_time":1.70615758,"remaining_time":0.3298299857},
{"learn":[0.01265807268],"iteration":838,"passed_time":1.708336687,"remaining_time":0.327821462},
{"learn":[0.01258557317],"iteration":839,"passed_time":1.710431069,"remaining_time":0.3257963942},
{"learn":[0.01251356722],"iteration":840,"passed_time":1.712585694,"remaining_time":0.3237825509},
{"learn":[0.01244205059],"iteration":841,"passed_time":1.714772511,"remaining_time":0.3217744141},
{"learn":[0.01238694204],"iteration":842,"passed_time":1.716523987,"remaining_time":0.3196847758},
{"learn":[0.01233215367],"iteration":843,"passed_time":1.718510705,"remaining_time":0.3176394194},
{"learn":[0.01226161648],"iteration":844,"passed_time":1.721555135,"remaining_time":0.31578822},
{"learn":[0.01220739122],"iteration":845,"passed_time":1.723342003,"remaining_time":0.3137052818},
{"learn":[0.01215029306],"iteration":846,"passed_time":1.725602588,"remaining_time":0.3117086139},
{"learn":[0.01208077385],"iteration":847,"passed_time":1.727722701,"remaining_time":0.3096861445},
{"learn":[0.01202737706],"iteration":848,"passed_time":1.729438307,"remaining_time":0.307591501},
{"learn":[0.01197115749],"iteration":849,"passed_time":1.731576797,"remaining_time":0.305572376},
{"learn":[0.01191833956],"iteration":850,"passed_time":1.733300909,"remaining_time":0.3034804178},
{"learn":[0.01186269779],"iteration":851,"passed_time":1.736757728,"remaining_time":0.3016903096},
{"learn":[0.01180584725],"iteration":852,"passed_time":1.738584922,"remaining_time":0.2996154554},
{"learn":[0.01174370996],"iteration":853,"passed_time":1.740926689,"remaining_time":0.2976291529},
{"learn":[0.01168197891],"iteration":854,"passed_time":1.743093777,"remaining_time":0.2956123949},
{"learn":[0.01162851303],"iteration":855,"passed_time":1.745353311,"remaining_time":0.2936108374},
{"learn":[0.01156744539],"iteration":856,"passed_time":1.747559071,"remaining_time":0.2915997049},
{"learn":[0.01150677657],"iteration":857,"passed_time":1.750589314,"remaining_time":0.2897245718},
{"learn":[0.01145413161],"iteration":858,"passed_time":1.752906965,"remaining_time":0.2877297813},
{"learn":[0.01139411523],"iteration":859,"passed_time":1.755078841,"remaining_time":0.2857105091},
{"learn":[0.01133449042],"iteration":860,"passed_time":1.757145431,"remaining_time":0.2836738849},
{"learn":[0.01128265479],"iteration":861,"passed_time":1.75927827,"remaining_time":0.2816477973},
{"learn":[0.01122367168],"iteration":862,"passed_time":1.761536432,"remaining_time":0.2796413571},
{"learn":[0.01116507303],"iteration":863,"passed_time":1.763893725,"remaining_time":0.2776499382},
{"learn":[0.01111403533],"iteration":864,"passed_time":1.766826777,"remaining_time":0.2757475316},
{"learn":[0.01106326755],"iteration":865,"passed_time":1.769108821,"remaining_time":0.2737420116},
{"learn":[0.01100871632],"iteration":866,"passed_time":1.771277437,"remaining_time":0.2717184534},
{"learn":[0.01095846564],"iteration":867,"passed_time":1.773446804,"remaining_time":0.2696946752},
{"learn":[0.01090445834],"iteration":868,"passed_time":1.775735834,"remaining_time":0.267688601},
{"learn":[0.01085473057],"iteration":869,"passed_time":1.777912997,"remaining_time":0.2656651604},
{"learn":[0.01079210481],"iteration":870,"passed_time":1.781063139,"remaining_time":0.2637854706},
{"learn":[0.01072990993],"iteration":871,"passed_time":1.783459524,"remaining_time":0.2617922237},
{"learn":[0.01068282634],"iteration":872,"passed_time":1.785198726,"remaining_time":0.2597024492},
{"learn":[0.01062126792],"iteration":873,"passed_time":1.787398752,"remaining_time":0.2576799116},
{"learn":[0.01057466705],"iteration":874,"passed_time":1.78912275,"remaining_time":0.2555889643},
{"learn":[0.01051942493],"iteration":875,"passed_time":1.791259002,"remaining_time":0.2535572103},
{"learn":[0.01046454396],"iteration":876,"passed_time":1.79338492,"remaining_time":0.2515237687},
{"learn":[0.01041678581],"iteration":877,"passed_time":1.796674761,"remaining_time":0.249651846},
{"learn":[0.01036928044],"iteration":878,"passed_time":1.798833366,"remaining_time":0.2476209753},
{"learn":[0.01032392174],"iteration":879,"passed_time":1.800515576,"remaining_time":0.2455248513},
{"learn":[0.01027010425],"iteration":880,"passed_time":1.802993199,"remaining_time":0.2435371063},
{"learn":[0.01021663933],"iteration":881,"passed_time":1.805312899,"remaining_time":0.2415271226},
{"learn":[0.01017009482],"iteration":882,"passed_time":1.807582922,"remaining_time":0.2395098549},
{"learn":[0.01012379689],"iteration":883,"passed_time":1.810218664,"remaining_time":0.2375400056},
{"learn":[0.01007393439],"iteration":884,"passed_time":1.813661099,"remaining_time":0.2356734761},
{"learn":[0.01002810785],"iteration":885,"passed_time":1.815782327,"remaining_time":0.2336333919},
{"learn":[0.009970030193],"iteration":886,"passed_time":1.817859393,"remaining_time":0.2315874988},
{"learn":[0.009926534541],"iteration":887,"passed_time":1.819586319,"remaining_time":0.2294973736},
{"learn":[0.009881423773],"iteration":888,"passed_time":1.821767691,"remaining_time":0.2274648073},
{"learn":[0.00982416072],"iteration":889,"passed_time":1.824086141,"remaining_time":0.2254488489},
{"learn":[0.00976729441],"iteration":890,"passed_time":1.827453722,"remaining_time":0.2235605563},
{"learn":[0.009710821362],"iteration":891,"passed_time":1.829624308,"remaining_time":0.2215240194},
{"learn":[0.009654738128],"iteration":892,"passed_time":1.831760706,"remaining_time":0.2194830857},
{"learn":[0.0095990413],"iteration":893,"passed_time":1.83410674,"remaining_time":0.2174667947},
{"learn":[0.009543727504],"iteration":894,"passed_time":1.836253436,"remaining_time":0.2154263808},
{"learn":[0.009488793405],"iteration":895,"passed_time":1.838398446,"remaining_time":0.2133855339},
{"learn":[0.009434235701],"iteration":896,"passed_time":1.842329827,"remaining_time":0.2115495788},
{"learn":[0.009392724104],"iteration":897,"passed_time":1.845251625,"remaining_time":0.2095942826},
{"learn":[0.009351454147],"iteration":898,"passed_time":1.847761921,"remaining_time":0.2075906051},
{"learn":[0.009310424653],"iteration":899,"passed_time":1.84943509,"remaining_time":0.2054927878},
{"learn":[0.009269634454],"iteration":900,"passed_time":1.851132357,"remaining_time":0.2033985609},
{"learn":[0.009216181776],"iteration":901,"passed_time":1.853352192,"remaining_time":0.2013619898},
{"learn":[0.009175809393],"iteration":902,"passed_time":1.855583027,"remaining_time":0.1993261945},
{"learn":[0.009122903502],"iteration":903,"passed_time":1.859222391,"remaining_time":0.197439546},
{"learn":[0.009082944635],"iteration":904,"passed_time":1.860990457,"remaining_time":0.1953525894},
{"learn":[0.009035596361],"iteration":905,"passed_time":1.863387647,"remaining_time":0.1933316102},
{"learn":[0.00898855728],"iteration":906,"passed_time":1.866250729,"remaining_time":0.191357572},
{"learn":[0.008941825008],"iteration":907,"passed_time":1.868519597,"remaining_time":0.1893213688},
{"learn":[0.008895397186],"iteration":908,"passed_time":1.871411685,"remaining_time":0.1873470444},
{"learn":[0.008849271482],"iteration":909,"passed_time":1.874447933,"remaining_time":0.1853849604},
{"learn":[0.00880344559],"iteration":910,"passed_time":1.876773035,"remaining_time":0.1833510429},
{"learn":[0.008757917225],"iteration":911,"passed_time":1.879079275,"remaining_time":0.1813146668},
{"learn":[0.008717873937],"iteration":912,"passed_time":1.881946058,"remaining_time":0.179331114},
{"learn":[0.00867805324],"iteration":913,"passed_time":1.884298835,"remaining_time":0.1772972646},
{"learn":[0.008638442282],"iteration":914,"passed_time":1.887605682,"remaining_time":0.1753513475},
{"learn":[0.008593794533],"iteration":915,"passed_time":1.889941965,"remaining_time":0.1733134553},
{"learn":[0.008554596918],"iteration":916,"passed_time":1.892121083,"remaining_time":0.1712606869},
{"learn":[0.008515605892],"iteration":917,"passed_time":1.894335596,"remaining_time":0.1692108049},
{"learn":[0.008476832001],"iteration":918,"passed_time":1.896605769,"remaining_time":0.1671654704},
{"learn":[0.008438262592],"iteration":919,"passed_time":1.899093532,"remaining_time":0.165138568},
{"learn":[0.008401574786],"iteration":920,"passed_time":1.901522455,"remaining_time":0.1631056178},
{"learn":[0.008363415274],"iteration":921,"passed_time":1.903881355,"remaining_time":0.1610658847},
{"learn":[0.008325457157],"iteration":922,"passed_time":1.906126545,"remaining_time":0.159015974},
{"learn":[0.008277042686],"iteration":923,"passed_time":1.908714518,"remaining_time":0.1569938348},
{"learn":[0.008241114801],"iteration":924,"passed_time":1.910673386,"remaining_time":0.1549194637},
{"learn":[0.008198520552],"iteration":925,"passed_time":1.912936425,"remaining_time":0.1528696495},
{"learn":[0.008161332529],"iteration":926,"passed_time":1.915423308,"remaining_time":0.1508370027},
{"learn":[0.008113834648],"iteration":927,"passed_time":1.918665513,"remaining_time":0.1488619794},
{"learn":[0.008066667845],"iteration":928,"passed_time":1.921230057,"remaining_time":0.1468324371},
{"learn":[0.008031638072],"iteration":929,"passed_time":1.923020062,"remaining_time":0.1447434455},
{"learn":[0.007996813903],"iteration":930,"passed_time":1.924765687,"remaining_time":0.1426518071},
{"learn":[0.007955526403],"iteration":931,"passed_time":1.926962973,"remaining_time":0.1405938649},
{"learn":[0.007919444038],"iteration":932,"passed_time":1.929407473,"remaining_time":0.138553377},
{"learn":[0.007878604793],"iteration":933,"passed_time":1.932649086,"remaining_time":0.1365683509},
{"learn":[0.007842900225],"iteration":934,"passed_time":1.935332476,"remaining_time":0.1345418298},
{"learn":[0.007807383929],"iteration":935,"passed_time":1.937515206,"remaining_time":0.1324796722},
{"learn":[0.007773675434],"iteration":936,"passed_time":1.939341186,"remaining_time":0.1303932708},
{"learn":[0.007735462293],"iteration":937,"passed_time":1.941680013,"remaining_time":0.1283413228},
{"learn":[0.007700486264],"iteration":938,"passed_time":1.944012153,"remaining_time":0.1262883295},
{"learn":[0.007662653619],"iteration":939,"passed_time":1.947368464,"remaining_time":0.1243001147},
{"learn":[0.007628042413],"iteration":940,"passed_time":1.949747075,"remaining_time":0.1222476912},
{"learn":[0.007595229897],"iteration":941,"passed_time":1.951552682,"remaining_time":0.1201592947},
{"learn":[0.007560411618],"iteration":942,"passed_time":1.9540517,"remaining_time":0.1181134113},
{"learn":[0.007525082113],"iteration":943,"passed_time":1.955800993,"remaining_time":0.1160220928},
{"learn":[0.007488145499],"iteration":944,"passed_time":1.958271288,"remaining_time":0.1139734612},
{"learn":[0.007454413264],"iteration":945,"passed_time":1.961349726,"remaining_time":0.1119586525},
{"learn":[0.007417850724],"iteration":946,"passed_time":1.963972006,"remaining_time":0.1099160679},
{"learn":[0.007384466294],"iteration":947,"passed_time":1.966132822,"remaining_time":0.1078469481},
{"learn":[0.007351275987],"iteration":948,"passed_time":1.968800908,"remaining_time":0.105804896},
{"learn":[0.007308072374],"iteration":949,"passed_time":1.971575238,"remaining_time":0.1037671178},
{"learn":[0.007265174925],"iteration":950,"passed_time":1.97453663,"remaining_time":0.1017374289},
{"learn":[0.007222580889],"iteration":951,"passed_time":1.977700764,"remaining_time":0.09971600489},
{"learn":[0.007180287545],"iteration":952,"passed_time":1.979861845,"remaining_time":0.09764271429},
{"learn":[0.007149404889],"iteration":953,"passed_time":1.98157894,"remaining_time":0.09554783147},
{"learn":[0.007118705059],"iteration":954,"passed_time":1.983276306,"remaining_time":0.09345281022},
{"learn":[0.007088187165],"iteration":955,"passed_time":1.985020568,"remaining_time":0.09136077928},
{"learn":[0.007056304232],"iteration":956,"passed_time":1.987239641,"remaining_time":0.08929080937},
{"learn":[0.007026129094],"iteration":957,"passed_time":1.989503391,"remaining_time":0.08722248688},
{"learn":[0.006994039716],"iteration":958,"passed_time":1.992607116,"remaining_time":0.08518966814},
{"learn":[0.006961467002],"iteration":959,"passed_time":1.994967799,"remaining_time":0.08312365827},
{"learn":[0.00693023093],"iteration":960,"passed_time":1.99715264,"remaining_time":0.08104989902},
{"learn":[0.006896297578],"iteration":961,"passed_time":1.99938065,"remaining_time":0.07897761402},
{"learn":[0.006865381533],"iteration":962,"passed_time":2.001546454,"remaining_time":0.07690261556},
{"learn":[0.006834645867],"iteration":963,"passed_time":2.003750092,"remaining_time":0.07482884161},
{"learn":[0.00680289084],"iteration":964,"passed_time":2.005925803,"remaining_time":0.07275378559},
{"learn":[0.006769600571],"iteration":965,"passed_time":2.009059899,"remaining_time":0.07071225316},
{"learn":[0.006739322941],"iteration":966,"passed_time":2.011315529,"remaining_time":0.06863848238},
{"learn":[0.006709222196],"iteration":967,"passed_time":2.013470467,"remaining_time":0.06656100718},
{"learn":[0.006676406842],"iteration":968,"passed_time":2.015688126,"remaining_time":0.06448537864},
{"learn":[0.006636916069],"iteration":969,"passed_time":2.017919598,"remaining_time":0.06240988448},
{"learn":[0.006597708329],"iteration":970,"passed_time":2.020168801,"remaining_time":0.06033459859},
{"learn":[0.006569674572],"iteration":971,"passed_time":2.022719468,"remaining_time":0.058267639},
{"learn":[0.00653086794],"iteration":972,"passed_time":2.024952789,"remaining_time":0.05619087905},
{"learn":[0.006503121582],"iteration":973,"passed_time":2.026691072,"remaining_time":0.05410058302},
{"learn":[0.006474055171],"iteration":974,"passed_time":2.02882811,"remaining_time":0.0520212336},
{"learn":[0.006435786851],"iteration":975,"passed_time":2.031112113,"remaining_time":0.04994537983},
{"learn":[0.006408471225],"iteration":976,"passed_time":2.032827266,"remaining_time":0.04785570842},
{"learn":[0.006379855349],"iteration":977,"passed_time":2.035009619,"remaining_time":0.0457773125},
{"learn":[0.006352847998],"iteration":978,"passed_time":2.03828876,"remaining_time":0.0437222308},
{"learn":[0.006324009615],"iteration":979,"passed_time":2.042234795,"remaining_time":0.04167826112},
{"learn":[0.006294734907],"iteration":980,"passed_time":2.044533369,"remaining_time":0.03959850563},
{"learn":[0.00626670668],"iteration":981,"passed_time":2.046749446,"remaining_time":0.03751679228},
{"learn":[0.006238821659],"iteration":982,"passed_time":2.048958888,"remaining_time":0.03543469083},
{"learn":[0.006208376535],"iteration":983,"passed_time":2.051805621,"remaining_time":0.03336269302},
{"learn":[0.006180774561],"iteration":984,"passed_time":2.055182953,"remaining_time":0.03129720233},
{"learn":[0.00614403381],"iteration":985,"passed_time":2.057426555,"remaining_time":0.02921295312},
{"learn":[0.006107558567],"iteration":986,"passed_time":2.059615234,"remaining_time":0.02712765758},
{"learn":[0.006071346404],"iteration":987,"passed_time":2.061833348,"remaining_time":0.02504251029},
{"learn":[0.006035394918],"iteration":988,"passed_time":2.06436558,"remaining_time":0.02296058785},
{"learn":[0.005999701735],"iteration":989,"passed_time":2.067203516,"remaining_time":0.0208808436},
{"learn":[0.005964264506],"iteration":990,"passed_time":2.070014097,"remaining_time":0.01879932076},
{"learn":[0.005929080906],"iteration":991,"passed_time":2.072107089,"remaining_time":0.01671054104},
{"learn":[0.005903856763],"iteration":992,"passed_time":2.073776611,"remaining_time":0.01461876765},
{"learn":[0.005878783437],"iteration":993,"passed_time":2.07553514,"remaining_time":0.01252838113},
{"learn":[0.005853860188],"iteration":994,"passed_time":2.077300936,"remaining_time":0.01043869817},
{"learn":[0.005819251862],"iteration":995,"passed_time":2.079547948,"remaining_time":0.008351598185},
{"learn":[0.005794584282],"iteration":996,"passed_time":2.081839109,"remaining_time":0.006264310258},
{"learn":[0.005760330198],"iteration":997,"passed_time":2.084442225,"remaining_time":0.004177238929},
{"learn":[0.005726321777],"iteration":998,"passed_time":2.086576404,"remaining_time":0.002088665069},
{"learn":[0.005702012174],"iteration":999,"passed_time":2.088244912,"remaining_time":0}
]}